[{"gene":"AARS2","log2":1.5028468917,"sampleID":"TCGA-B8-4622","pvalue":0,"mutation":""},{"gene":"ABCB7","log2":0.4129483418,"sampleID":"TCGA-B8-4622","pvalue":0,"mutation":""},{"gene":"ACAA2","log2":-0.2499750099,"sampleID":"TCGA-B8-4622","pvalue":0,"mutation":""},{"gene":"ACAD10","log2":0.4197875497,"sampleID":"TCGA-B8-4622","pvalue":0,"mutation":""},{"gene":"ACAD11","log2":1.659721443,"sampleID":"TCGA-B8-4622","pvalue":0,"mutation":""},{"gene":"ACAD8","log2":-1.0656264596,"sampleID":"TCGA-B8-4622","pvalue":0,"mutation":""},{"gene":"ACAD9","log2":0.4416232912,"sampleID":"TCGA-B8-4622","pvalue":0,"mutation":""},{"gene":"ACADL","log2":1.3921958075,"sampleID":"TCGA-B8-4622","pvalue":0,"mutation":""},{"gene":"ACADM","log2":-1.0028067871,"sampleID":"TCGA-B8-4622","pvalue":0,"mutation":""},{"gene":"ACADSB","log2":-1.2809472884,"sampleID":"TCGA-B8-4622","pvalue":0,"mutation":""},{"gene":"ACADS","log2":0.9110052838,"sampleID":"TCGA-B8-4622","pvalue":0,"mutation":""},{"gene":"ACADVL","log2":1.0723539946,"sampleID":"TCGA-B8-4622","pvalue":0,"mutation":""},{"gene":"ACO2","log2":-0.1067535933,"sampleID":"TCGA-B8-4622","pvalue":0,"mutation":""},{"gene":"ACSBG1","log2":-0.4773695482,"sampleID":"TCGA-B8-4622","pvalue":0,"mutation":""},{"gene":"ACSBG2","log2":-3.4277085252,"sampleID":"TCGA-B8-4622","pvalue":0,"mutation":""},{"gene":"ACSL1","log2":-0.3722413452,"sampleID":"TCGA-B8-4622","pvalue":0,"mutation":""},{"gene":"ACSL3","log2":-0.8876479518,"sampleID":"TCGA-B8-4622","pvalue":0,"mutation":""},{"gene":"ACSL4","log2":-2.5787493414,"sampleID":"TCGA-B8-4622","pvalue":0,"mutation":""},{"gene":"ACSL5","log2":0.2498536443,"sampleID":"TCGA-B8-4622","pvalue":0,"mutation":""},{"gene":"ACSL6","log2":-4.2757051379,"sampleID":"TCGA-B8-4622","pvalue":0,"mutation":""},{"gene":"ACSM1","log2":-3.3179488193,"sampleID":"TCGA-B8-4622","pvalue":0,"mutation":""},{"gene":"ACSM2A","log2":0.0158057918,"sampleID":"TCGA-B8-4622","pvalue":0,"mutation":""},{"gene":"ACSM2B","log2":0.1516205231,"sampleID":"TCGA-B8-4622","pvalue":0,"mutation":""},{"gene":"ACSM3","log2":-2.411990384,"sampleID":"TCGA-B8-4622","pvalue":0,"mutation":""},{"gene":"ACSM5","log2":1.0652845994,"sampleID":"TCGA-B8-4622","pvalue":0,"mutation":""},{"gene":"ACSS1","log2":0.8810955821,"sampleID":"TCGA-B8-4622","pvalue":0,"mutation":""},{"gene":"ACSS2","log2":0.1914827039,"sampleID":"TCGA-B8-4622","pvalue":0,"mutation":""},{"gene":"ACSS3","log2":-1.2653195295,"sampleID":"TCGA-B8-4622","pvalue":0,"mutation":""},{"gene":"AFG3L2","log2":0.5027206248,"sampleID":"TCGA-B8-4622","pvalue":0,"mutation":""},{"gene":"AIFM1","log2":-1.7912141489,"sampleID":"TCGA-B8-4622","pvalue":0,"mutation":""},{"gene":"AK3","log2":-1.8863335613,"sampleID":"TCGA-B8-4622","pvalue":0,"mutation":""},{"gene":"ALAD","log2":-1.3240331416,"sampleID":"TCGA-B8-4622","pvalue":0,"mutation":""},{"gene":"ALAS1","log2":-0.8483739595,"sampleID":"TCGA-B8-4622","pvalue":0,"mutation":""},{"gene":"ALAS2","log2":1.2306503753,"sampleID":"TCGA-B8-4622","pvalue":0,"mutation":""},{"gene":"ALDOA","log2":1.8486941122,"sampleID":"TCGA-B8-4622","pvalue":0,"mutation":""},{"gene":"ALDOB","log2":-6.6017596098,"sampleID":"TCGA-B8-4622","pvalue":0,"mutation":""},{"gene":"ALDOC","log2":4.892690556,"sampleID":"TCGA-B8-4622","pvalue":0,"mutation":""},{"gene":"AMBRA1","log2":0.4885864977,"sampleID":"TCGA-B8-4622","pvalue":0,"mutation":""},{"gene":"ANP32A","log2":0.3258270692,"sampleID":"TCGA-B8-4622","pvalue":0,"mutation":""},{"gene":"APAF1","log2":1.3709221143,"sampleID":"TCGA-B8-4622","pvalue":0,"mutation":""},{"gene":"APEX1","log2":0.6975478452,"sampleID":"TCGA-B8-4622","pvalue":0,"mutation":""},{"gene":"APEX2","log2":0.1397891761,"sampleID":"TCGA-B8-4622","pvalue":0,"mutation":""},{"gene":"ARG1","log2":2.3869819723,"sampleID":"TCGA-B8-4622","pvalue":0,"mutation":""},{"gene":"ARG2","log2":-2.2359935035,"sampleID":"TCGA-B8-4622","pvalue":0,"mutation":""},{"gene":"ASL","log2":-0.6302251249,"sampleID":"TCGA-B8-4622","pvalue":0,"mutation":""},{"gene":"ASS1","log2":-4.0950680024,"sampleID":"TCGA-B8-4622","pvalue":0,"mutation":""},{"gene":"ATAD3A","log2":0.9076902235,"sampleID":"TCGA-B8-4622","pvalue":0,"mutation":""},{"gene":"ATAD3B","log2":3.2204230803,"sampleID":"TCGA-B8-4622","pvalue":0,"mutation":""},{"gene":"ATP5A1","log2":-1.1874758818,"sampleID":"TCGA-B8-4622","pvalue":0,"mutation":""},{"gene":"ATP5B","log2":-0.2171659999,"sampleID":"TCGA-B8-4622","pvalue":0,"mutation":""},{"gene":"ATP5C1","log2":-0.9677074965,"sampleID":"TCGA-B8-4622","pvalue":0,"mutation":""},{"gene":"ATP5D","log2":-0.1353305945,"sampleID":"TCGA-B8-4622","pvalue":0,"mutation":""},{"gene":"ATP5E","log2":-0.3004331205,"sampleID":"TCGA-B8-4622","pvalue":0,"mutation":""},{"gene":"ATP5F1","log2":-0.776080038,"sampleID":"TCGA-B8-4622","pvalue":0,"mutation":""},{"gene":"ATP5G1","log2":-1.4281867341,"sampleID":"TCGA-B8-4622","pvalue":0,"mutation":""},{"gene":"ATP5G2","log2":0.4436532663,"sampleID":"TCGA-B8-4622","pvalue":0,"mutation":""},{"gene":"ATP5G3","log2":-1.1717628368,"sampleID":"TCGA-B8-4622","pvalue":0,"mutation":""},{"gene":"ATP5H","log2":-0.5776751577,"sampleID":"TCGA-B8-4622","pvalue":0,"mutation":""},{"gene":"ATP5I","log2":-0.5879027791,"sampleID":"TCGA-B8-4622","pvalue":0,"mutation":""},{"gene":"ATP5J2","log2":-0.8072242806,"sampleID":"TCGA-B8-4622","pvalue":0,"mutation":""},{"gene":"ATP5J","log2":-1.3291114306,"sampleID":"TCGA-B8-4622","pvalue":0,"mutation":""},{"gene":"ATP5L","log2":-1.0036785489,"sampleID":"TCGA-B8-4622","pvalue":0,"mutation":""},{"gene":"ATP5O","log2":-0.4094216704,"sampleID":"TCGA-B8-4622","pvalue":0,"mutation":""},{"gene":"ATPAF1","log2":-0.5465931669,"sampleID":"TCGA-B8-4622","pvalue":0,"mutation":""},{"gene":"ATPAF2","log2":-0.1953967694,"sampleID":"TCGA-B8-4622","pvalue":0,"mutation":""},{"gene":"ATPIF1","log2":-0.8305650026,"sampleID":"TCGA-B8-4622","pvalue":0,"mutation":""},{"gene":"BAD","log2":-0.039205126,"sampleID":"TCGA-B8-4622","pvalue":0,"mutation":""},{"gene":"BAK1","log2":0.2362044043,"sampleID":"TCGA-B8-4622","pvalue":0,"mutation":""},{"gene":"BAX","log2":0.7122342755,"sampleID":"TCGA-B8-4622","pvalue":0,"mutation":""},{"gene":"BBC3","log2":1.1688612502,"sampleID":"TCGA-B8-4622","pvalue":0,"mutation":""},{"gene":"BCKDHA","log2":0.7338640007,"sampleID":"TCGA-B8-4622","pvalue":0,"mutation":""},{"gene":"BCKDHB","log2":-1.4610010894,"sampleID":"TCGA-B8-4622","pvalue":0,"mutation":""},{"gene":"BCL2L11","log2":0.7308599538,"sampleID":"TCGA-B8-4622","pvalue":0,"mutation":""},{"gene":"BCL2L1","log2":-0.0123598349,"sampleID":"TCGA-B8-4622","pvalue":0,"mutation":""},{"gene":"BCL2","log2":1.6556832421,"sampleID":"TCGA-B8-4622","pvalue":0,"mutation":""},{"gene":"BCS1L","log2":0.5221164963,"sampleID":"TCGA-B8-4622","pvalue":0,"mutation":""},{"gene":"BECN1","log2":0.2058098599,"sampleID":"TCGA-B8-4622","pvalue":0,"mutation":""},{"gene":"BID","log2":0.5689499146,"sampleID":"TCGA-B8-4622","pvalue":0,"mutation":""},{"gene":"BIK","log2":-5.8391998038,"sampleID":"TCGA-B8-4622","pvalue":0,"mutation":""},{"gene":"BNIP3L","log2":1.409933164,"sampleID":"TCGA-B8-4622","pvalue":0,"mutation":""},{"gene":"BNIP3","log2":1.7308053424,"sampleID":"TCGA-B8-4622","pvalue":0,"mutation":""},{"gene":"BOLA3","log2":-0.3849282277,"sampleID":"TCGA-B8-4622","pvalue":0,"mutation":""},{"gene":"BRP44L","log2":-1.3758414601,"sampleID":"TCGA-B8-4622","pvalue":0,"mutation":""},{"gene":"BRP44","log2":-0.812967075,"sampleID":"TCGA-B8-4622","pvalue":0,"mutation":""},{"gene":"C10orf2","log2":0.1916456529,"sampleID":"TCGA-B8-4622","pvalue":0,"mutation":""},{"gene":"C1orf31","log2":-0.3928360904,"sampleID":"TCGA-B8-4622","pvalue":0,"mutation":""},{"gene":"C20orf7","log2":-0.6185438181,"sampleID":"TCGA-B8-4622","pvalue":0,"mutation":""},{"gene":"C22orf32","log2":-0.961040889,"sampleID":"TCGA-B8-4622","pvalue":0,"mutation":""},{"gene":"C2orf56","log2":-0.3330771063,"sampleID":"TCGA-B8-4622","pvalue":0,"mutation":""},{"gene":"C7orf44","log2":-0.2353307733,"sampleID":"TCGA-B8-4622","pvalue":0,"mutation":""},{"gene":"C8orf38","log2":-0.3789726472,"sampleID":"TCGA-B8-4622","pvalue":0,"mutation":""},{"gene":"CARS2","log2":0.4833936583,"sampleID":"TCGA-B8-4622","pvalue":0,"mutation":""},{"gene":"CASP3","log2":-0.0106842867,"sampleID":"TCGA-B8-4622","pvalue":0,"mutation":""},{"gene":"CASP7","log2":0.5423842102,"sampleID":"TCGA-B8-4622","pvalue":0,"mutation":""},{"gene":"CASP9","log2":-0.3851798332,"sampleID":"TCGA-B8-4622","pvalue":0,"mutation":""},{"gene":"CCDC109B","log2":-0.2085226663,"sampleID":"TCGA-B8-4622","pvalue":0,"mutation":""},{"gene":"CCDC56","log2":-0.5804735629,"sampleID":"TCGA-B8-4622","pvalue":0,"mutation":""},{"gene":"CCDC90A","log2":-0.9329766735,"sampleID":"TCGA-B8-4622","pvalue":0,"mutation":""},{"gene":"CD36","log2":3.3119984856,"sampleID":"TCGA-B8-4622","pvalue":0,"mutation":""},{"gene":"CDK1","log2":0.3446259841,"sampleID":"TCGA-B8-4622","pvalue":0,"mutation":""},{"gene":"CDK5RAP1","log2":0.4752513371,"sampleID":"TCGA-B8-4622","pvalue":0,"mutation":""},{"gene":"CDKAL1","log2":0.4164434857,"sampleID":"TCGA-B8-4622","pvalue":0,"mutation":""},{"gene":"CDS1","log2":-0.7682407485,"sampleID":"TCGA-B8-4622","pvalue":0,"mutation":""},{"gene":"CHCHD4","log2":-0.5024964547,"sampleID":"TCGA-B8-4622","pvalue":0,"mutation":""},{"gene":"CHCHD8","log2":0.1731372038,"sampleID":"TCGA-B8-4622","pvalue":0,"mutation":""},{"gene":"CIAO1","log2":0.2482676073,"sampleID":"TCGA-B8-4622","pvalue":0,"mutation":""},{"gene":"CIAPIN1","log2":-0.325560155,"sampleID":"TCGA-B8-4622","pvalue":0,"mutation":""},{"gene":"CLPP","log2":0.334096373,"sampleID":"TCGA-B8-4622","pvalue":0,"mutation":""},{"gene":"CLPX","log2":0.2843210069,"sampleID":"TCGA-B8-4622","pvalue":0,"mutation":""},{"gene":"CMPK2","log2":0.8854818349,"sampleID":"TCGA-B8-4622","pvalue":0,"mutation":""},{"gene":"COX10","log2":-0.0844658071,"sampleID":"TCGA-B8-4622","pvalue":0,"mutation":""},{"gene":"COX11","log2":-0.729391856,"sampleID":"TCGA-B8-4622","pvalue":0,"mutation":""},{"gene":"COX15","log2":0.2473820849,"sampleID":"TCGA-B8-4622","pvalue":0,"mutation":""},{"gene":"COX17","log2":-0.3606214563,"sampleID":"TCGA-B8-4622","pvalue":0,"mutation":""},{"gene":"COX18","log2":-0.4011535268,"sampleID":"TCGA-B8-4622","pvalue":0,"mutation":""},{"gene":"COX19","log2":2.2040289888,"sampleID":"TCGA-B8-4622","pvalue":0,"mutation":""},{"gene":"COX4I1","log2":-0.7688536469,"sampleID":"TCGA-B8-4622","pvalue":0,"mutation":""},{"gene":"COX4I2","log2":2.4640943774,"sampleID":"TCGA-B8-4622","pvalue":0,"mutation":""},{"gene":"COX5A","log2":-0.9026530194,"sampleID":"TCGA-B8-4622","pvalue":0,"mutation":""},{"gene":"COX5B","log2":-0.1892213913,"sampleID":"TCGA-B8-4622","pvalue":0,"mutation":""},{"gene":"COX6A1","log2":-0.2950579305,"sampleID":"TCGA-B8-4622","pvalue":0,"mutation":""},{"gene":"COX6A2","log2":-1.4467607428,"sampleID":"TCGA-B8-4622","pvalue":0,"mutation":""},{"gene":"COX6B1","log2":-0.5393860463,"sampleID":"TCGA-B8-4622","pvalue":0,"mutation":""},{"gene":"COX6B2","log2":-0.720730517,"sampleID":"TCGA-B8-4622","pvalue":0,"mutation":""},{"gene":"COX6C","log2":-0.0606993261,"sampleID":"TCGA-B8-4622","pvalue":0,"mutation":""},{"gene":"COX7A1","log2":-1.0120705792,"sampleID":"TCGA-B8-4622","pvalue":0,"mutation":""},{"gene":"COX7A2","log2":-0.7443738186,"sampleID":"TCGA-B8-4622","pvalue":0,"mutation":""},{"gene":"COX7B","log2":-1.2811796723,"sampleID":"TCGA-B8-4622","pvalue":0,"mutation":""},{"gene":"COX7C","log2":-0.8065201161,"sampleID":"TCGA-B8-4622","pvalue":0,"mutation":""},{"gene":"COX8A","log2":-0.8596563423,"sampleID":"TCGA-B8-4622","pvalue":0,"mutation":""},{"gene":"CPOX","log2":1.3098247255,"sampleID":"TCGA-B8-4622","pvalue":0,"mutation":""},{"gene":"CPS1","log2":-3.0520400071,"sampleID":"TCGA-B8-4622","pvalue":0,"mutation":""},{"gene":"CPT1A","log2":0.6568502397,"sampleID":"TCGA-B8-4622","pvalue":0,"mutation":""},{"gene":"CPT1B","log2":1.4662269373,"sampleID":"TCGA-B8-4622","pvalue":0,"mutation":""},{"gene":"CPT1C","log2":1.7666245862,"sampleID":"TCGA-B8-4622","pvalue":0,"mutation":""},{"gene":"CPT2","log2":-0.2048774841,"sampleID":"TCGA-B8-4622","pvalue":0,"mutation":""},{"gene":"CRAT","log2":-0.5987133725,"sampleID":"TCGA-B8-4622","pvalue":0,"mutation":""},{"gene":"CREB1","log2":0.1677427414,"sampleID":"TCGA-B8-4622","pvalue":0,"mutation":""},{"gene":"CRLS1","log2":-0.0526925885,"sampleID":"TCGA-B8-4622","pvalue":0,"mutation":""},{"gene":"CS","log2":0.4848376042,"sampleID":"TCGA-B8-4622","pvalue":0,"mutation":""},{"gene":"CYC1","log2":-0.4660705963,"sampleID":"TCGA-B8-4622","pvalue":0,"mutation":""},{"gene":"CYCS","log2":-1.0560110692,"sampleID":"TCGA-B8-4622","pvalue":0,"mutation":""},{"gene":"DAP3","log2":-0.3391371006,"sampleID":"TCGA-B8-4622","pvalue":0,"mutation":""},{"gene":"DARS2","log2":-0.0734725866,"sampleID":"TCGA-B8-4622","pvalue":0,"mutation":""},{"gene":"DDX28","log2":-0.3374012483,"sampleID":"TCGA-B8-4622","pvalue":0,"mutation":""},{"gene":"DECR1","log2":-0.8577577809,"sampleID":"TCGA-B8-4622","pvalue":0,"mutation":""},{"gene":"DHX30","log2":-0.0051927538,"sampleID":"TCGA-B8-4622","pvalue":0,"mutation":""},{"gene":"DIABLO","log2":-0.0869036519,"sampleID":"TCGA-B8-4622","pvalue":0,"mutation":""},{"gene":"DLAT","log2":-0.2479003494,"sampleID":"TCGA-B8-4622","pvalue":0,"mutation":""},{"gene":"DLD","log2":-0.3957119626,"sampleID":"TCGA-B8-4622","pvalue":0,"mutation":""},{"gene":"DLST","log2":-0.2318679844,"sampleID":"TCGA-B8-4622","pvalue":0,"mutation":""},{"gene":"DNAJC19","log2":-0.5818547549,"sampleID":"TCGA-B8-4622","pvalue":0,"mutation":""},{"gene":"DNM1L","log2":0.1615578293,"sampleID":"TCGA-B8-4622","pvalue":0,"mutation":""},{"gene":"DNM1","log2":-0.5100949738,"sampleID":"TCGA-B8-4622","pvalue":0,"mutation":""},{"gene":"DUS2L","log2":0.2043367603,"sampleID":"TCGA-B8-4622","pvalue":0,"mutation":""},{"gene":"DYNLL1","log2":0.1804720447,"sampleID":"TCGA-B8-4622","pvalue":0,"mutation":""},{"gene":"EARS2","log2":0.2175030654,"sampleID":"TCGA-B8-4622","pvalue":0,"mutation":""},{"gene":"ECHS1","log2":-1.9661786437,"sampleID":"TCGA-B8-4622","pvalue":0,"mutation":""},{"gene":"ECSIT","log2":-0.0006603457,"sampleID":"TCGA-B8-4622","pvalue":0,"mutation":""},{"gene":"EFHA1","log2":-1.1480515075,"sampleID":"TCGA-B8-4622","pvalue":0,"mutation":""},{"gene":"EFHA2","log2":0.0350322685,"sampleID":"TCGA-B8-4622","pvalue":0,"mutation":""},{"gene":"EIF3M","log2":-0.4263888604,"sampleID":"TCGA-B8-4622","pvalue":0,"mutation":""},{"gene":"ELAC2","log2":0.087712777,"sampleID":"TCGA-B8-4622","pvalue":0,"mutation":""},{"gene":"ENDOG","log2":-0.8653620295,"sampleID":"TCGA-B8-4622","pvalue":0,"mutation":""},{"gene":"ENO1","log2":1.7552714249,"sampleID":"TCGA-B8-4622","pvalue":0,"mutation":""},{"gene":"ENO2","log2":5.4266681084,"sampleID":"TCGA-B8-4622","pvalue":0,"mutation":""},{"gene":"ENO3","log2":-0.1559385259,"sampleID":"TCGA-B8-4622","pvalue":0,"mutation":""},{"gene":"FABP1","log2":-9.1622295333,"sampleID":"TCGA-B8-4622","pvalue":0,"mutation":""},{"gene":"FABP2","log2":0.0629374379,"sampleID":"TCGA-B8-4622","pvalue":0,"mutation":""},{"gene":"FABP3","log2":-0.0519981501,"sampleID":"TCGA-B8-4622","pvalue":0,"mutation":""},{"gene":"FABP4","log2":-3.1057681403,"sampleID":"TCGA-B8-4622","pvalue":0,"mutation":""},{"gene":"FABP5","log2":3.5165230539,"sampleID":"TCGA-B8-4622","pvalue":0,"mutation":""},{"gene":"FABP6","log2":8.4778071347,"sampleID":"TCGA-B8-4622","pvalue":0,"mutation":""},{"gene":"FABP7","log2":8.0728841891,"sampleID":"TCGA-B8-4622","pvalue":0,"mutation":""},{"gene":"FAM96A","log2":-0.3974349666,"sampleID":"TCGA-B8-4622","pvalue":0,"mutation":""},{"gene":"FAM96B","log2":-0.1228539015,"sampleID":"TCGA-B8-4622","pvalue":0,"mutation":""},{"gene":"FARS2","log2":0.102155799,"sampleID":"TCGA-B8-4622","pvalue":0,"mutation":""},{"gene":"FDX1L","log2":-0.5717918002,"sampleID":"TCGA-B8-4622","pvalue":0,"mutation":""},{"gene":"FDX1","log2":-1.5103799584,"sampleID":"TCGA-B8-4622","pvalue":0,"mutation":""},{"gene":"FDXR","log2":0.7514991473,"sampleID":"TCGA-B8-4622","pvalue":0,"mutation":""},{"gene":"FECH","log2":-0.5508817821,"sampleID":"TCGA-B8-4622","pvalue":0,"mutation":""},{"gene":"FH","log2":-0.9615997809,"sampleID":"TCGA-B8-4622","pvalue":0,"mutation":""},{"gene":"FIS1","log2":-0.3035885664,"sampleID":"TCGA-B8-4622","pvalue":0,"mutation":""},{"gene":"FOXRED1","log2":-0.5449715511,"sampleID":"TCGA-B8-4622","pvalue":0,"mutation":""},{"gene":"FXN","log2":-0.3516241149,"sampleID":"TCGA-B8-4622","pvalue":0,"mutation":""},{"gene":"GABARAP","log2":-0.2680179006,"sampleID":"TCGA-B8-4622","pvalue":0,"mutation":""},{"gene":"GAPDHS","log2":3.2673774676,"sampleID":"TCGA-B8-4622","pvalue":0,"mutation":""},{"gene":"GAPDH","log2":1.9983697149,"sampleID":"TCGA-B8-4622","pvalue":0,"mutation":""},{"gene":"GARS","log2":-0.2546603027,"sampleID":"TCGA-B8-4622","pvalue":0,"mutation":""},{"gene":"GATC","log2":0.5911910443,"sampleID":"TCGA-B8-4622","pvalue":0,"mutation":""},{"gene":"GCK","log2":-1.5377450505,"sampleID":"TCGA-B8-4622","pvalue":0,"mutation":""},{"gene":"GCLC","log2":0.0716159834,"sampleID":"TCGA-B8-4622","pvalue":0,"mutation":""},{"gene":"GCLM","log2":0.3564379444,"sampleID":"TCGA-B8-4622","pvalue":0,"mutation":""},{"gene":"GDAP1","log2":-0.2272016832,"sampleID":"TCGA-B8-4622","pvalue":0,"mutation":""},{"gene":"GFER","log2":0.3672590522,"sampleID":"TCGA-B8-4622","pvalue":0,"mutation":""},{"gene":"GFM1","log2":-0.9631933134,"sampleID":"TCGA-B8-4622","pvalue":0,"mutation":""},{"gene":"GFM2","log2":0.1493243486,"sampleID":"TCGA-B8-4622","pvalue":0,"mutation":""},{"gene":"GLRX2","log2":-0.5719095318,"sampleID":"TCGA-B8-4622","pvalue":0,"mutation":""},{"gene":"GLRX5","log2":-1.259732054,"sampleID":"TCGA-B8-4622","pvalue":0,"mutation":""},{"gene":"GOT2","log2":-1.0033796653,"sampleID":"TCGA-B8-4622","pvalue":0,"mutation":""},{"gene":"GPI","log2":1.6858366835,"sampleID":"TCGA-B8-4622","pvalue":0,"mutation":""},{"gene":"GPX1","log2":-0.1908414454,"sampleID":"TCGA-B8-4622","pvalue":0,"mutation":""},{"gene":"GPX4","log2":0.1853746798,"sampleID":"TCGA-B8-4622","pvalue":0,"mutation":""},{"gene":"GRPEL1","log2":0.1578403411,"sampleID":"TCGA-B8-4622","pvalue":0,"mutation":""},{"gene":"GRPEL2","log2":0.7748576144,"sampleID":"TCGA-B8-4622","pvalue":0,"mutation":""},{"gene":"GSR","log2":-0.0888025419,"sampleID":"TCGA-B8-4622","pvalue":0,"mutation":""},{"gene":"GSS","log2":0.0752037467,"sampleID":"TCGA-B8-4622","pvalue":0,"mutation":""},{"gene":"GSTA1","log2":-0.3520898152,"sampleID":"TCGA-B8-4622","pvalue":0,"mutation":""},{"gene":"GSTA2","log2":1.5617418816,"sampleID":"TCGA-B8-4622","pvalue":0,"mutation":""},{"gene":"GSTA4","log2":-0.0619227769,"sampleID":"TCGA-B8-4622","pvalue":0,"mutation":""},{"gene":"GSTP1","log2":0.5506723633,"sampleID":"TCGA-B8-4622","pvalue":0,"mutation":""},{"gene":"GTPBP3","log2":1.9108973349,"sampleID":"TCGA-B8-4622","pvalue":0,"mutation":""},{"gene":"HADHA","log2":0.2703591284,"sampleID":"TCGA-B8-4622","pvalue":0,"mutation":""},{"gene":"HADHB","log2":0.0379215876,"sampleID":"TCGA-B8-4622","pvalue":0,"mutation":""},{"gene":"HADH","log2":-2.2780623573,"sampleID":"TCGA-B8-4622","pvalue":0,"mutation":""},{"gene":"HARS2","log2":0.9888002253,"sampleID":"TCGA-B8-4622","pvalue":0,"mutation":""},{"gene":"HCCS","log2":-0.5510324766,"sampleID":"TCGA-B8-4622","pvalue":0,"mutation":""},{"gene":"HK1","log2":1.1657698101,"sampleID":"TCGA-B8-4622","pvalue":0,"mutation":""},{"gene":"HK2","log2":3.9354606031,"sampleID":"TCGA-B8-4622","pvalue":0,"mutation":""},{"gene":"HK3","log2":2.5736640774,"sampleID":"TCGA-B8-4622","pvalue":0,"mutation":""},{"gene":"HMBS","log2":-0.8276154862,"sampleID":"TCGA-B8-4622","pvalue":0,"mutation":""},{"gene":"HSCB","log2":-0.1082994845,"sampleID":"TCGA-B8-4622","pvalue":0,"mutation":""},{"gene":"HSD17B10","log2":-1.2274432801,"sampleID":"TCGA-B8-4622","pvalue":0,"mutation":""},{"gene":"HSPA9","log2":-0.0090927455,"sampleID":"TCGA-B8-4622","pvalue":0,"mutation":""},{"gene":"HTRA2","log2":0.4929161419,"sampleID":"TCGA-B8-4622","pvalue":0,"mutation":""},{"gene":"IARS2","log2":0.43930738,"sampleID":"TCGA-B8-4622","pvalue":0,"mutation":""},{"gene":"IDH1","log2":-1.3122567722,"sampleID":"TCGA-B8-4622","pvalue":0,"mutation":""},{"gene":"IDH2","log2":-0.3802035003,"sampleID":"TCGA-B8-4622","pvalue":0,"mutation":""},{"gene":"IDH3A","log2":-0.3874469545,"sampleID":"TCGA-B8-4622","pvalue":0,"mutation":""},{"gene":"IDH3B","log2":0.6009434586,"sampleID":"TCGA-B8-4622","pvalue":0,"mutation":""},{"gene":"IDH3G","log2":-0.3707921133,"sampleID":"TCGA-B8-4622","pvalue":0,"mutation":""},{"gene":"IMMP1L","log2":-0.4408329025,"sampleID":"TCGA-B8-4622","pvalue":0,"mutation":""},{"gene":"IMMP2L","log2":0.6226358316,"sampleID":"TCGA-B8-4622","pvalue":0,"mutation":""},{"gene":"ISCA1","log2":-1.2197154554,"sampleID":"TCGA-B8-4622","pvalue":0,"mutation":""},{"gene":"ISCA2","log2":-0.4101688486,"sampleID":"TCGA-B8-4622","pvalue":0,"mutation":""},{"gene":"ISCU","log2":-0.1981238327,"sampleID":"TCGA-B8-4622","pvalue":0,"mutation":""},{"gene":"ITPR1","log2":1.2411050624,"sampleID":"TCGA-B8-4622","pvalue":0,"mutation":""},{"gene":"ITPR2","log2":-0.3677660892,"sampleID":"TCGA-B8-4622","pvalue":0,"mutation":""},{"gene":"ITPR3","log2":1.9265197367,"sampleID":"TCGA-B8-4622","pvalue":0,"mutation":""},{"gene":"KARS","log2":0.2081436972,"sampleID":"TCGA-B8-4622","pvalue":0,"mutation":""},{"gene":"KIAA0391","log2":-0.5721335301,"sampleID":"TCGA-B8-4622","pvalue":0,"mutation":""},{"gene":"KIF1B","log2":0.322454233,"sampleID":"TCGA-B8-4622","pvalue":0,"mutation":""},{"gene":"KIF5B","log2":0.0425096551,"sampleID":"TCGA-B8-4622","pvalue":0,"mutation":""},{"gene":"LARS2","log2":-1.0240860975,"sampleID":"TCGA-B8-4622","pvalue":0,"mutation":""},{"gene":"LDHAL6B","log2":2.6433851993,"sampleID":"TCGA-B8-4622","pvalue":0,"mutation":""},{"gene":"LDHA","log2":2.4658119548,"sampleID":"TCGA-B8-4622","pvalue":0,"mutation":""},{"gene":"LDHB","log2":-0.9302164209,"sampleID":"TCGA-B8-4622","pvalue":0,"mutation":""},{"gene":"LDHC","log2":-1.6604438833,"sampleID":"TCGA-B8-4622","pvalue":0,"mutation":""},{"gene":"LETM1","log2":-0.298033071,"sampleID":"TCGA-B8-4622","pvalue":0,"mutation":""},{"gene":"LIG3","log2":0.8575534094,"sampleID":"TCGA-B8-4622","pvalue":0,"mutation":""},{"gene":"LONP1","log2":0.5038612721,"sampleID":"TCGA-B8-4622","pvalue":0,"mutation":""},{"gene":"LRPPRC","log2":0.0103866042,"sampleID":"TCGA-B8-4622","pvalue":0,"mutation":""},{"gene":"LYRM4","log2":-0.5536255219,"sampleID":"TCGA-B8-4622","pvalue":0,"mutation":""},{"gene":"MAP1LC3A","log2":-0.563892074,"sampleID":"TCGA-B8-4622","pvalue":0,"mutation":""},{"gene":"MAPK1","log2":0.5060991037,"sampleID":"TCGA-B8-4622","pvalue":0,"mutation":""},{"gene":"MAPK3","log2":0.7649517184,"sampleID":"TCGA-B8-4622","pvalue":0,"mutation":""},{"gene":"MARCH5","log2":-0.4741742657,"sampleID":"TCGA-B8-4622","pvalue":0,"mutation":""},{"gene":"MARS2","log2":-0.7497312765,"sampleID":"TCGA-B8-4622","pvalue":0,"mutation":""},{"gene":"MCL1","log2":0.2725195257,"sampleID":"TCGA-B8-4622","pvalue":0,"mutation":""},{"gene":"MDH2","log2":-0.0692189654,"sampleID":"TCGA-B8-4622","pvalue":0,"mutation":""},{"gene":"MFF","log2":-0.0199593301,"sampleID":"TCGA-B8-4622","pvalue":0,"mutation":""},{"gene":"MFN1","log2":-0.0699933939,"sampleID":"TCGA-B8-4622","pvalue":0,"mutation":""},{"gene":"MFN2","log2":-0.1369177129,"sampleID":"TCGA-B8-4622","pvalue":0,"mutation":""},{"gene":"MIPEP","log2":-0.8709753646,"sampleID":"TCGA-B8-4622","pvalue":0,"mutation":""},{"gene":"MMS19","log2":0.616953842,"sampleID":"TCGA-B8-4622","pvalue":0,"mutation":""},{"gene":"MPV17L2","log2":-1.254262363,"sampleID":"TCGA-B8-4622","pvalue":0,"mutation":""},{"gene":"MPV17L","log2":-0.621049501,"sampleID":"TCGA-B8-4622","pvalue":0,"mutation":""},{"gene":"MPV17","log2":0.5493155659,"sampleID":"TCGA-B8-4622","pvalue":0,"mutation":""},{"gene":"MRPL10","log2":0.0257217902,"sampleID":"TCGA-B8-4622","pvalue":0,"mutation":""},{"gene":"MRPL11","log2":0.2778686855,"sampleID":"TCGA-B8-4622","pvalue":0,"mutation":""},{"gene":"MRPL12","log2":-0.4667745287,"sampleID":"TCGA-B8-4622","pvalue":0,"mutation":""},{"gene":"MRPL13","log2":-0.9530375748,"sampleID":"TCGA-B8-4622","pvalue":0,"mutation":""},{"gene":"MRPL14","log2":-0.6391494968,"sampleID":"TCGA-B8-4622","pvalue":0,"mutation":""},{"gene":"MRPL15","log2":-0.5623883537,"sampleID":"TCGA-B8-4622","pvalue":0,"mutation":""},{"gene":"MRPL16","log2":0.1892159481,"sampleID":"TCGA-B8-4622","pvalue":0,"mutation":""},{"gene":"MRPL17","log2":0.0628035089,"sampleID":"TCGA-B8-4622","pvalue":0,"mutation":""},{"gene":"MRPL18","log2":-0.0763063397,"sampleID":"TCGA-B8-4622","pvalue":0,"mutation":""},{"gene":"MRPL19","log2":-1.0143217701,"sampleID":"TCGA-B8-4622","pvalue":0,"mutation":""},{"gene":"MRPL1","log2":-0.7708830334,"sampleID":"TCGA-B8-4622","pvalue":0,"mutation":""},{"gene":"MRPL20","log2":-0.3794934427,"sampleID":"TCGA-B8-4622","pvalue":0,"mutation":""},{"gene":"MRPL21","log2":-0.1827714999,"sampleID":"TCGA-B8-4622","pvalue":0,"mutation":""},{"gene":"MRPL22","log2":-0.375871375,"sampleID":"TCGA-B8-4622","pvalue":0,"mutation":""},{"gene":"MRPL23","log2":0.3658260467,"sampleID":"TCGA-B8-4622","pvalue":0,"mutation":""},{"gene":"MRPL24","log2":-0.2685317658,"sampleID":"TCGA-B8-4622","pvalue":0,"mutation":""},{"gene":"MRPL27","log2":-0.0749654335,"sampleID":"TCGA-B8-4622","pvalue":0,"mutation":""},{"gene":"MRPL28","log2":-0.1055951811,"sampleID":"TCGA-B8-4622","pvalue":0,"mutation":""},{"gene":"MRPL2","log2":-0.1621424461,"sampleID":"TCGA-B8-4622","pvalue":0,"mutation":""},{"gene":"MRPL30","log2":0.343873062,"sampleID":"TCGA-B8-4622","pvalue":0,"mutation":""},{"gene":"MRPL32","log2":-0.2077356665,"sampleID":"TCGA-B8-4622","pvalue":0,"mutation":""},{"gene":"MRPL33","log2":-0.8314108859,"sampleID":"TCGA-B8-4622","pvalue":0,"mutation":""},{"gene":"MRPL35","log2":-0.4683113668,"sampleID":"TCGA-B8-4622","pvalue":0,"mutation":""},{"gene":"MRPL36","log2":-0.5544202737,"sampleID":"TCGA-B8-4622","pvalue":0,"mutation":""},{"gene":"MRPL37","log2":-0.114426348,"sampleID":"TCGA-B8-4622","pvalue":0,"mutation":""},{"gene":"MRPL38","log2":-0.3238029482,"sampleID":"TCGA-B8-4622","pvalue":0,"mutation":""},{"gene":"MRPL39","log2":-0.2910866369,"sampleID":"TCGA-B8-4622","pvalue":0,"mutation":""},{"gene":"MRPL3","log2":-0.8663979775,"sampleID":"TCGA-B8-4622","pvalue":0,"mutation":""},{"gene":"MRPL40","log2":-0.1989523304,"sampleID":"TCGA-B8-4622","pvalue":0,"mutation":""},{"gene":"MRPL41","log2":-1.3404762357,"sampleID":"TCGA-B8-4622","pvalue":0,"mutation":""},{"gene":"MRPL42","log2":-0.1839754983,"sampleID":"TCGA-B8-4622","pvalue":0,"mutation":""},{"gene":"MRPL43","log2":0.1133759378,"sampleID":"TCGA-B8-4622","pvalue":0,"mutation":""},{"gene":"MRPL44","log2":-0.3688733986,"sampleID":"TCGA-B8-4622","pvalue":0,"mutation":""},{"gene":"MRPL45","log2":-0.2677411611,"sampleID":"TCGA-B8-4622","pvalue":0,"mutation":""},{"gene":"MRPL46","log2":-0.2302250115,"sampleID":"TCGA-B8-4622","pvalue":0,"mutation":""},{"gene":"MRPL47","log2":-0.9801098523,"sampleID":"TCGA-B8-4622","pvalue":0,"mutation":""},{"gene":"MRPL48","log2":-0.1915452307,"sampleID":"TCGA-B8-4622","pvalue":0,"mutation":""},{"gene":"MRPL49","log2":-0.6325839234,"sampleID":"TCGA-B8-4622","pvalue":0,"mutation":""},{"gene":"MRPL4","log2":-0.0759620929,"sampleID":"TCGA-B8-4622","pvalue":0,"mutation":""},{"gene":"MRPL50","log2":-0.9836574901,"sampleID":"TCGA-B8-4622","pvalue":0,"mutation":""},{"gene":"MRPL51","log2":0.4421681081,"sampleID":"TCGA-B8-4622","pvalue":0,"mutation":""},{"gene":"MRPL52","log2":-0.54522354,"sampleID":"TCGA-B8-4622","pvalue":0,"mutation":""},{"gene":"MRPL53","log2":-0.1283722603,"sampleID":"TCGA-B8-4622","pvalue":0,"mutation":""},{"gene":"MRPL54","log2":-0.4532854711,"sampleID":"TCGA-B8-4622","pvalue":0,"mutation":""},{"gene":"MRPL55","log2":0.132053734,"sampleID":"TCGA-B8-4622","pvalue":0,"mutation":""},{"gene":"MRPL9","log2":-0.0244701754,"sampleID":"TCGA-B8-4622","pvalue":0,"mutation":""},{"gene":"MRPS10","log2":-0.5670785966,"sampleID":"TCGA-B8-4622","pvalue":0,"mutation":""},{"gene":"MRPS11","log2":-0.5705426324,"sampleID":"TCGA-B8-4622","pvalue":0,"mutation":""},{"gene":"MRPS12","log2":-0.1386869336,"sampleID":"TCGA-B8-4622","pvalue":0,"mutation":""},{"gene":"MRPS14","log2":-0.0416443136,"sampleID":"TCGA-B8-4622","pvalue":0,"mutation":""},{"gene":"MRPS15","log2":-0.4949495428,"sampleID":"TCGA-B8-4622","pvalue":0,"mutation":""},{"gene":"MRPS16","log2":-0.3434038251,"sampleID":"TCGA-B8-4622","pvalue":0,"mutation":""},{"gene":"MRPS17","log2":0.4527199325,"sampleID":"TCGA-B8-4622","pvalue":0,"mutation":""},{"gene":"MRPS18A","log2":-0.0214699557,"sampleID":"TCGA-B8-4622","pvalue":0,"mutation":""},{"gene":"MRPS18B","log2":0.0098303064,"sampleID":"TCGA-B8-4622","pvalue":0,"mutation":""},{"gene":"MRPS18C","log2":-0.655939059,"sampleID":"TCGA-B8-4622","pvalue":0,"mutation":""},{"gene":"MRPS21","log2":-0.1365873016,"sampleID":"TCGA-B8-4622","pvalue":0,"mutation":""},{"gene":"MRPS22","log2":-0.4894354426,"sampleID":"TCGA-B8-4622","pvalue":0,"mutation":""},{"gene":"MRPS23","log2":-0.1781010418,"sampleID":"TCGA-B8-4622","pvalue":0,"mutation":""},{"gene":"MRPS24","log2":0.4257275002,"sampleID":"TCGA-B8-4622","pvalue":0,"mutation":""},{"gene":"MRPS25","log2":-0.7001642201,"sampleID":"TCGA-B8-4622","pvalue":0,"mutation":""},{"gene":"MRPS26","log2":0.220138734,"sampleID":"TCGA-B8-4622","pvalue":0,"mutation":""},{"gene":"MRPS27","log2":-0.1055290939,"sampleID":"TCGA-B8-4622","pvalue":0,"mutation":""},{"gene":"MRPS28","log2":-0.6935371356,"sampleID":"TCGA-B8-4622","pvalue":0,"mutation":""},{"gene":"MRPS2","log2":-0.2470865852,"sampleID":"TCGA-B8-4622","pvalue":0,"mutation":""},{"gene":"MRPS30","log2":-0.2836395985,"sampleID":"TCGA-B8-4622","pvalue":0,"mutation":""},{"gene":"MRPS31","log2":-0.3809620321,"sampleID":"TCGA-B8-4622","pvalue":0,"mutation":""},{"gene":"MRPS33","log2":-0.1972861473,"sampleID":"TCGA-B8-4622","pvalue":0,"mutation":""},{"gene":"MRPS34","log2":0.4029031818,"sampleID":"TCGA-B8-4622","pvalue":0,"mutation":""},{"gene":"MRPS35","log2":-0.4501204849,"sampleID":"TCGA-B8-4622","pvalue":0,"mutation":""},{"gene":"MRPS36","log2":-0.9193559673,"sampleID":"TCGA-B8-4622","pvalue":0,"mutation":""},{"gene":"MRPS5","log2":0.1202815273,"sampleID":"TCGA-B8-4622","pvalue":0,"mutation":""},{"gene":"MRPS6","log2":-0.09602523,"sampleID":"TCGA-B8-4622","pvalue":0,"mutation":""},{"gene":"MRPS7","log2":-0.2407654647,"sampleID":"TCGA-B8-4622","pvalue":0,"mutation":""},{"gene":"MRPS9","log2":-0.4628460375,"sampleID":"TCGA-B8-4622","pvalue":0,"mutation":""},{"gene":"MRRF","log2":-0.2120700449,"sampleID":"TCGA-B8-4622","pvalue":0,"mutation":""},{"gene":"MSTO1","log2":0.557250833,"sampleID":"TCGA-B8-4622","pvalue":0,"mutation":""},{"gene":"MTFMT","log2":0.3620756901,"sampleID":"TCGA-B8-4622","pvalue":0,"mutation":""},{"gene":"MTIF2","log2":0.764646049,"sampleID":"TCGA-B8-4622","pvalue":0,"mutation":""},{"gene":"MTIF3","log2":-0.1370326871,"sampleID":"TCGA-B8-4622","pvalue":0,"mutation":""},{"gene":"MTO1","log2":0.2291885126,"sampleID":"TCGA-B8-4622","pvalue":0,"mutation":""},{"gene":"MTPAP","log2":0.2619519364,"sampleID":"TCGA-B8-4622","pvalue":0,"mutation":""},{"gene":"MTRF1L","log2":-0.4565847378,"sampleID":"TCGA-B8-4622","pvalue":0,"mutation":""},{"gene":"MTRF1","log2":0.4360600775,"sampleID":"TCGA-B8-4622","pvalue":0,"mutation":""},{"gene":"MUTYH","log2":0.5813698372,"sampleID":"TCGA-B8-4622","pvalue":0,"mutation":""},{"gene":"NARF","log2":1.2362210754,"sampleID":"TCGA-B8-4622","pvalue":0,"mutation":""},{"gene":"NARS2","log2":-0.3576916253,"sampleID":"TCGA-B8-4622","pvalue":0,"mutation":""},{"gene":"NDUFA10","log2":-0.2404245152,"sampleID":"TCGA-B8-4622","pvalue":0,"mutation":""},{"gene":"NDUFA11","log2":-0.7674984438,"sampleID":"TCGA-B8-4622","pvalue":0,"mutation":""},{"gene":"NDUFA12","log2":0.3233586078,"sampleID":"TCGA-B8-4622","pvalue":0,"mutation":""},{"gene":"NDUFA13","log2":-0.8148476628,"sampleID":"TCGA-B8-4622","pvalue":0,"mutation":""},{"gene":"NDUFA1","log2":-0.410151345,"sampleID":"TCGA-B8-4622","pvalue":0,"mutation":""},{"gene":"NDUFA2","log2":-0.848656843,"sampleID":"TCGA-B8-4622","pvalue":0,"mutation":""},{"gene":"NDUFA3","log2":-1.103827817,"sampleID":"TCGA-B8-4622","pvalue":0,"mutation":""},{"gene":"NDUFA4","log2":-1.2978404705,"sampleID":"TCGA-B8-4622","pvalue":0,"mutation":""},{"gene":"NDUFA5","log2":0.0830885971,"sampleID":"TCGA-B8-4622","pvalue":0,"mutation":""},{"gene":"NDUFA6","log2":-0.9173950036,"sampleID":"TCGA-B8-4622","pvalue":0,"mutation":""},{"gene":"NDUFA7","log2":-0.4579857793,"sampleID":"TCGA-B8-4622","pvalue":0,"mutation":""},{"gene":"NDUFA8","log2":-0.492879895,"sampleID":"TCGA-B8-4622","pvalue":0,"mutation":""},{"gene":"NDUFA9","log2":-0.8162195115,"sampleID":"TCGA-B8-4622","pvalue":0,"mutation":""},{"gene":"NDUFAB1","log2":-0.483582537,"sampleID":"TCGA-B8-4622","pvalue":0,"mutation":""},{"gene":"NDUFAF1","log2":-0.535587738,"sampleID":"TCGA-B8-4622","pvalue":0,"mutation":""},{"gene":"NDUFAF2","log2":-0.1044500015,"sampleID":"TCGA-B8-4622","pvalue":0,"mutation":""},{"gene":"NDUFAF3","log2":-0.6782426904,"sampleID":"TCGA-B8-4622","pvalue":0,"mutation":""},{"gene":"NDUFAF4","log2":-0.7406562319,"sampleID":"TCGA-B8-4622","pvalue":0,"mutation":""},{"gene":"NDUFB10","log2":0.0764487876,"sampleID":"TCGA-B8-4622","pvalue":0,"mutation":""},{"gene":"NDUFB11","log2":-0.2864244465,"sampleID":"TCGA-B8-4622","pvalue":0,"mutation":""},{"gene":"NDUFB1","log2":-1.073714757,"sampleID":"TCGA-B8-4622","pvalue":0,"mutation":""},{"gene":"NDUFB2","log2":-1.1946534695,"sampleID":"TCGA-B8-4622","pvalue":0,"mutation":""},{"gene":"NDUFB3","log2":-1.2306919295,"sampleID":"TCGA-B8-4622","pvalue":0,"mutation":""},{"gene":"NDUFB4","log2":-0.0317558504,"sampleID":"TCGA-B8-4622","pvalue":0,"mutation":""},{"gene":"NDUFB5","log2":-1.2872436715,"sampleID":"TCGA-B8-4622","pvalue":0,"mutation":""},{"gene":"NDUFB6","log2":-1.3740713385,"sampleID":"TCGA-B8-4622","pvalue":0,"mutation":""},{"gene":"NDUFB7","log2":-0.6993469148,"sampleID":"TCGA-B8-4622","pvalue":0,"mutation":""},{"gene":"NDUFB8","log2":-0.7226081454,"sampleID":"TCGA-B8-4622","pvalue":0,"mutation":""},{"gene":"NDUFB9","log2":-0.9855254061,"sampleID":"TCGA-B8-4622","pvalue":0,"mutation":""},{"gene":"NDUFC1","log2":-0.2276488201,"sampleID":"TCGA-B8-4622","pvalue":0,"mutation":""},{"gene":"NDUFC2","log2":-0.7468859966,"sampleID":"TCGA-B8-4622","pvalue":0,"mutation":""},{"gene":"NDUFS1","log2":-0.6738606246,"sampleID":"TCGA-B8-4622","pvalue":0,"mutation":""},{"gene":"NDUFS2","log2":-0.2967678951,"sampleID":"TCGA-B8-4622","pvalue":0,"mutation":""},{"gene":"NDUFS3","log2":-0.6059685392,"sampleID":"TCGA-B8-4622","pvalue":0,"mutation":""},{"gene":"NDUFS4","log2":-0.4303576198,"sampleID":"TCGA-B8-4622","pvalue":0,"mutation":""},{"gene":"NDUFS5","log2":-0.2786284709,"sampleID":"TCGA-B8-4622","pvalue":0,"mutation":""},{"gene":"NDUFS6","log2":-0.7315120937,"sampleID":"TCGA-B8-4622","pvalue":0,"mutation":""},{"gene":"NDUFS7","log2":-0.7139610907,"sampleID":"TCGA-B8-4622","pvalue":0,"mutation":""},{"gene":"NDUFS8","log2":-1.3117053093,"sampleID":"TCGA-B8-4622","pvalue":0,"mutation":""},{"gene":"NDUFV1","log2":-0.4666149515,"sampleID":"TCGA-B8-4622","pvalue":0,"mutation":""},{"gene":"NDUFV2","log2":-0.4770549819,"sampleID":"TCGA-B8-4622","pvalue":0,"mutation":""},{"gene":"NDUFV3","log2":-0.172319372,"sampleID":"TCGA-B8-4622","pvalue":0,"mutation":""},{"gene":"NFE2L2","log2":-0.0277750176,"sampleID":"TCGA-B8-4622","pvalue":0,"mutation":""},{"gene":"NFS1","log2":0.1305508256,"sampleID":"TCGA-B8-4622","pvalue":0,"mutation":""},{"gene":"NFU1","log2":-0.1004608029,"sampleID":"TCGA-B8-4622","pvalue":0,"mutation":""},{"gene":"NME3","log2":0.7258771667,"sampleID":"TCGA-B8-4622","pvalue":0,"mutation":""},{"gene":"NME4","log2":1.2259579837,"sampleID":"TCGA-B8-4622","pvalue":0,"mutation":""},{"gene":"NME6","log2":-0.4863219997,"sampleID":"TCGA-B8-4622","pvalue":0,"mutation":""},{"gene":"NRF1","log2":0.9049397558,"sampleID":"TCGA-B8-4622","pvalue":0,"mutation":""},{"gene":"NSUN2","log2":0.6384542968,"sampleID":"TCGA-B8-4622","pvalue":0,"mutation":""},{"gene":"NTHL1","log2":0.1133615475,"sampleID":"TCGA-B8-4622","pvalue":0,"mutation":""},{"gene":"NUBP1","log2":0.2242317072,"sampleID":"TCGA-B8-4622","pvalue":0,"mutation":""},{"gene":"NUBP2","log2":-0.0306137437,"sampleID":"TCGA-B8-4622","pvalue":0,"mutation":""},{"gene":"NUBPL","log2":-0.4414976395,"sampleID":"TCGA-B8-4622","pvalue":0,"mutation":""},{"gene":"OGDH","log2":-0.0241833163,"sampleID":"TCGA-B8-4622","pvalue":0,"mutation":""},{"gene":"OGG1","log2":-1.0359086845,"sampleID":"TCGA-B8-4622","pvalue":0,"mutation":""},{"gene":"OMA1","log2":-0.8604134199,"sampleID":"TCGA-B8-4622","pvalue":0,"mutation":""},{"gene":"OPA1","log2":-0.3029604339,"sampleID":"TCGA-B8-4622","pvalue":0,"mutation":""},{"gene":"OPA3","log2":0.7727327865,"sampleID":"TCGA-B8-4622","pvalue":0,"mutation":""},{"gene":"OSGEPL1","log2":0.1344015273,"sampleID":"TCGA-B8-4622","pvalue":0,"mutation":""},{"gene":"OXA1L","log2":0.6791982627,"sampleID":"TCGA-B8-4622","pvalue":0,"mutation":""},{"gene":"PACS2","log2":1.3036835504,"sampleID":"TCGA-B8-4622","pvalue":0,"mutation":""},{"gene":"PARK2","log2":1.9303211786,"sampleID":"TCGA-B8-4622","pvalue":0,"mutation":""},{"gene":"PARL","log2":0.1847539752,"sampleID":"TCGA-B8-4622","pvalue":0,"mutation":""},{"gene":"PARS2","log2":-0.1064712928,"sampleID":"TCGA-B8-4622","pvalue":0,"mutation":""},{"gene":"PDHA1","log2":-0.9617053532,"sampleID":"TCGA-B8-4622","pvalue":0,"mutation":""},{"gene":"PDHB","log2":-1.3776023047,"sampleID":"TCGA-B8-4622","pvalue":0,"mutation":""},{"gene":"PDHX","log2":-0.5047088039,"sampleID":"TCGA-B8-4622","pvalue":0,"mutation":""},{"gene":"PFKL","log2":0.9284305398,"sampleID":"TCGA-B8-4622","pvalue":0,"mutation":""},{"gene":"PFKM","log2":-0.0331142105,"sampleID":"TCGA-B8-4622","pvalue":0,"mutation":""},{"gene":"PFKP","log2":3.3270858366,"sampleID":"TCGA-B8-4622","pvalue":0,"mutation":""},{"gene":"PGAM1","log2":1.3239940782,"sampleID":"TCGA-B8-4622","pvalue":0,"mutation":""},{"gene":"PGAM2","log2":0.0081717974,"sampleID":"TCGA-B8-4622","pvalue":0,"mutation":""},{"gene":"PGK1","log2":1.4890321804,"sampleID":"TCGA-B8-4622","pvalue":0,"mutation":""},{"gene":"PGS1","log2":1.2796229866,"sampleID":"TCGA-B8-4622","pvalue":0,"mutation":""},{"gene":"PHB2","log2":0.8439364276,"sampleID":"TCGA-B8-4622","pvalue":0,"mutation":""},{"gene":"PHB","log2":-0.9877657063,"sampleID":"TCGA-B8-4622","pvalue":0,"mutation":""},{"gene":"PINK1","log2":-0.3062984252,"sampleID":"TCGA-B8-4622","pvalue":0,"mutation":""},{"gene":"PKIA","log2":-3.1041838177,"sampleID":"TCGA-B8-4622","pvalue":0,"mutation":""},{"gene":"PKLR","log2":-1.7188424649,"sampleID":"TCGA-B8-4622","pvalue":0,"mutation":""},{"gene":"PKM2","log2":1.7602595166,"sampleID":"TCGA-B8-4622","pvalue":0,"mutation":""},{"gene":"PLD6","log2":0.6871340103,"sampleID":"TCGA-B8-4622","pvalue":0,"mutation":""},{"gene":"PMAIP1","log2":-1.4355361416,"sampleID":"TCGA-B8-4622","pvalue":0,"mutation":""},{"gene":"PML","log2":1.5768263698,"sampleID":"TCGA-B8-4622","pvalue":0,"mutation":""},{"gene":"PMPCA","log2":-0.1629810884,"sampleID":"TCGA-B8-4622","pvalue":0,"mutation":""},{"gene":"PMPCB","log2":0.2767344296,"sampleID":"TCGA-B8-4622","pvalue":0,"mutation":""},{"gene":"POLG2","log2":1.4358465136,"sampleID":"TCGA-B8-4622","pvalue":0,"mutation":""},{"gene":"POLG","log2":1.5993421383,"sampleID":"TCGA-B8-4622","pvalue":0,"mutation":""},{"gene":"POLRMT","log2":0.697013379,"sampleID":"TCGA-B8-4622","pvalue":0,"mutation":""},{"gene":"PPARGC1A","log2":0.0299994374,"sampleID":"TCGA-B8-4622","pvalue":0,"mutation":""},{"gene":"PPIA","log2":0.4371323087,"sampleID":"TCGA-B8-4622","pvalue":0,"mutation":""},{"gene":"PPIF","log2":-0.7059976794,"sampleID":"TCGA-B8-4622","pvalue":0,"mutation":""},{"gene":"PPOX","log2":0.4830511052,"sampleID":"TCGA-B8-4622","pvalue":0,"mutation":""},{"gene":"PRDX3","log2":-0.7748183102,"sampleID":"TCGA-B8-4622","pvalue":0,"mutation":""},{"gene":"PTCD2","log2":-0.6635071236,"sampleID":"TCGA-B8-4622","pvalue":0,"mutation":""},{"gene":"PTCD3","log2":0.1518788565,"sampleID":"TCGA-B8-4622","pvalue":0,"mutation":""},{"gene":"PTPMT1","log2":-0.5809814337,"sampleID":"TCGA-B8-4622","pvalue":0,"mutation":""},{"gene":"PUS1","log2":0.8039943821,"sampleID":"TCGA-B8-4622","pvalue":0,"mutation":""},{"gene":"PUS3","log2":-0.1880220297,"sampleID":"TCGA-B8-4622","pvalue":0,"mutation":""},{"gene":"QRSL1","log2":-0.1854607591,"sampleID":"TCGA-B8-4622","pvalue":0,"mutation":""},{"gene":"QTRT1","log2":1.0117581541,"sampleID":"TCGA-B8-4622","pvalue":0,"mutation":""},{"gene":"QTRTD1","log2":0.1129380585,"sampleID":"TCGA-B8-4622","pvalue":0,"mutation":""},{"gene":"RARS2","log2":-0.0733311118,"sampleID":"TCGA-B8-4622","pvalue":0,"mutation":""},{"gene":"RHOT1","log2":0.1437327435,"sampleID":"TCGA-B8-4622","pvalue":0,"mutation":""},{"gene":"RHOT2","log2":1.1288305545,"sampleID":"TCGA-B8-4622","pvalue":0,"mutation":""},{"gene":"RMRP","log2":-0.1105507674,"sampleID":"TCGA-B8-4622","pvalue":0,"mutation":""},{"gene":"RNASEH1","log2":-0.0907790353,"sampleID":"TCGA-B8-4622","pvalue":0,"mutation":""},{"gene":"RNASEL","log2":0.2715991989,"sampleID":"TCGA-B8-4622","pvalue":0,"mutation":""},{"gene":"RPUSD2","log2":0.0550603294,"sampleID":"TCGA-B8-4622","pvalue":0,"mutation":""},{"gene":"RPUSD4","log2":0.3917662229,"sampleID":"TCGA-B8-4622","pvalue":0,"mutation":""},{"gene":"RRM2B","log2":-0.231422826,"sampleID":"TCGA-B8-4622","pvalue":0,"mutation":""},{"gene":"SAMM50","log2":-0.1440490909,"sampleID":"TCGA-B8-4622","pvalue":0,"mutation":""},{"gene":"SARS2","log2":0.5312659304,"sampleID":"TCGA-B8-4622","pvalue":0,"mutation":""},{"gene":"SCO1","log2":-0.350006267,"sampleID":"TCGA-B8-4622","pvalue":0,"mutation":""},{"gene":"SCO2","log2":0.0362994893,"sampleID":"TCGA-B8-4622","pvalue":0,"mutation":""},{"gene":"SDHAF1","log2":-0.2638053307,"sampleID":"TCGA-B8-4622","pvalue":0,"mutation":""},{"gene":"SDHAF2","log2":-0.0566562694,"sampleID":"TCGA-B8-4622","pvalue":0,"mutation":""},{"gene":"SDHA","log2":0.5026146543,"sampleID":"TCGA-B8-4622","pvalue":0,"mutation":""},{"gene":"SDHB","log2":-0.7679952888,"sampleID":"TCGA-B8-4622","pvalue":0,"mutation":""},{"gene":"SDHC","log2":-0.7308221382,"sampleID":"TCGA-B8-4622","pvalue":0,"mutation":""},{"gene":"SDHD","log2":-0.9815572869,"sampleID":"TCGA-B8-4622","pvalue":0,"mutation":""},{"gene":"SH3GLB1","log2":0.4503796119,"sampleID":"TCGA-B8-4622","pvalue":0,"mutation":""},{"gene":"SHC1","log2":1.5034600504,"sampleID":"TCGA-B8-4622","pvalue":0,"mutation":""},{"gene":"SIGMAR1","log2":-0.5074785165,"sampleID":"TCGA-B8-4622","pvalue":0,"mutation":""},{"gene":"SLC24A6","log2":1.2482559148,"sampleID":"TCGA-B8-4622","pvalue":0,"mutation":""},{"gene":"SLC25A19","log2":0.7136902457,"sampleID":"TCGA-B8-4622","pvalue":0,"mutation":""},{"gene":"SLC25A1","log2":0.2371828974,"sampleID":"TCGA-B8-4622","pvalue":0,"mutation":""},{"gene":"SLC25A20","log2":-0.7146247872,"sampleID":"TCGA-B8-4622","pvalue":0,"mutation":""},{"gene":"SLC25A28","log2":0.4764447837,"sampleID":"TCGA-B8-4622","pvalue":0,"mutation":""},{"gene":"SLC25A33","log2":-1.2093582251,"sampleID":"TCGA-B8-4622","pvalue":0,"mutation":""},{"gene":"SLC25A37","log2":2.3626503579,"sampleID":"TCGA-B8-4622","pvalue":0,"mutation":""},{"gene":"SLC25A3","log2":-0.4224455195,"sampleID":"TCGA-B8-4622","pvalue":0,"mutation":""},{"gene":"SLC25A4","log2":-0.6494339188,"sampleID":"TCGA-B8-4622","pvalue":0,"mutation":""},{"gene":"SLC25A5","log2":-1.9144871743,"sampleID":"TCGA-B8-4622","pvalue":0,"mutation":""},{"gene":"SLC25A6","log2":0.3808383086,"sampleID":"TCGA-B8-4622","pvalue":0,"mutation":""},{"gene":"SLC27A1","log2":1.5679491762,"sampleID":"TCGA-B8-4622","pvalue":0,"mutation":""},{"gene":"SLC27A2","log2":-1.9767165583,"sampleID":"TCGA-B8-4622","pvalue":0,"mutation":""},{"gene":"SLC27A3","log2":1.7565739202,"sampleID":"TCGA-B8-4622","pvalue":0,"mutation":""},{"gene":"SLC27A4","log2":-1.6838742861,"sampleID":"TCGA-B8-4622","pvalue":0,"mutation":""},{"gene":"SLC27A5","log2":-0.9313826252,"sampleID":"TCGA-B8-4622","pvalue":0,"mutation":""},{"gene":"SLC29A1","log2":1.0736605266,"sampleID":"TCGA-B8-4622","pvalue":0,"mutation":""},{"gene":"SLC2A1","log2":3.0511102659,"sampleID":"TCGA-B8-4622","pvalue":0,"mutation":""},{"gene":"SLC2A2","log2":-0.8062513221,"sampleID":"TCGA-B8-4622","pvalue":0,"mutation":""},{"gene":"SLC2A3","log2":2.8224862737,"sampleID":"TCGA-B8-4622","pvalue":0,"mutation":""},{"gene":"SLC2A4","log2":-0.4244871782,"sampleID":"TCGA-B8-4622","pvalue":0,"mutation":""},{"gene":"SLC2A5","log2":2.1528080552,"sampleID":"TCGA-B8-4622","pvalue":0,"mutation":""},{"gene":"SOD1","log2":-0.8338095561,"sampleID":"TCGA-B8-4622","pvalue":0,"mutation":""},{"gene":"SOD2","log2":1.4751598169,"sampleID":"TCGA-B8-4622","pvalue":0,"mutation":""},{"gene":"SPG7","log2":0.8823265992,"sampleID":"TCGA-B8-4622","pvalue":0,"mutation":""},{"gene":"SQSTM1","log2":0.0053445716,"sampleID":"TCGA-B8-4622","pvalue":0,"mutation":""},{"gene":"SSBP1","log2":0.0459986762,"sampleID":"TCGA-B8-4622","pvalue":0,"mutation":""},{"gene":"STOML2","log2":-0.7692391052,"sampleID":"TCGA-B8-4622","pvalue":0,"mutation":""},{"gene":"SUCLA2","log2":-0.6494751737,"sampleID":"TCGA-B8-4622","pvalue":0,"mutation":""},{"gene":"SUCLG1","log2":-2.1538883879,"sampleID":"TCGA-B8-4622","pvalue":0,"mutation":""},{"gene":"SUCLG2","log2":-1.6361142776,"sampleID":"TCGA-B8-4622","pvalue":0,"mutation":""},{"gene":"SURF1","log2":-0.8983741513,"sampleID":"TCGA-B8-4622","pvalue":0,"mutation":""},{"gene":"SYBU","log2":3.8320135065,"sampleID":"TCGA-B8-4622","pvalue":0,"mutation":""},{"gene":"TACO1","log2":-0.7746181933,"sampleID":"TCGA-B8-4622","pvalue":0,"mutation":""},{"gene":"TARS2","log2":0.4257496803,"sampleID":"TCGA-B8-4622","pvalue":0,"mutation":""},{"gene":"TAZ","log2":1.7099959545,"sampleID":"TCGA-B8-4622","pvalue":0,"mutation":""},{"gene":"TCHP","log2":1.0788736309,"sampleID":"TCGA-B8-4622","pvalue":0,"mutation":""},{"gene":"TFAM","log2":-0.538137123,"sampleID":"TCGA-B8-4622","pvalue":0,"mutation":""},{"gene":"TFB1M","log2":0.112573917,"sampleID":"TCGA-B8-4622","pvalue":0,"mutation":""},{"gene":"TFB2M","log2":-0.9931749474,"sampleID":"TCGA-B8-4622","pvalue":0,"mutation":""},{"gene":"TIMM10","log2":-0.3125594953,"sampleID":"TCGA-B8-4622","pvalue":0,"mutation":""},{"gene":"TIMM13","log2":-0.3922975872,"sampleID":"TCGA-B8-4622","pvalue":0,"mutation":""},{"gene":"TIMM17A","log2":-0.5027565197,"sampleID":"TCGA-B8-4622","pvalue":0,"mutation":""},{"gene":"TIMM17B","log2":-0.4296293713,"sampleID":"TCGA-B8-4622","pvalue":0,"mutation":""},{"gene":"TIMM22","log2":0.1537385056,"sampleID":"TCGA-B8-4622","pvalue":0,"mutation":""},{"gene":"TIMM44","log2":0.6914322686,"sampleID":"TCGA-B8-4622","pvalue":0,"mutation":""},{"gene":"TIMM50","log2":-0.0806659019,"sampleID":"TCGA-B8-4622","pvalue":0,"mutation":""},{"gene":"TIMM8A","log2":-0.3322607312,"sampleID":"TCGA-B8-4622","pvalue":0,"mutation":""},{"gene":"TIMM8B","log2":-0.618799335,"sampleID":"TCGA-B8-4622","pvalue":0,"mutation":""},{"gene":"TIMM9","log2":0.1052063279,"sampleID":"TCGA-B8-4622","pvalue":0,"mutation":""},{"gene":"TK2","log2":-0.3091154788,"sampleID":"TCGA-B8-4622","pvalue":0,"mutation":""},{"gene":"TMEM126B","log2":-0.3948587564,"sampleID":"TCGA-B8-4622","pvalue":0,"mutation":""},{"gene":"TMEM70","log2":-0.5270617444,"sampleID":"TCGA-B8-4622","pvalue":0,"mutation":""},{"gene":"TOMM20","log2":0.1182590206,"sampleID":"TCGA-B8-4622","pvalue":0,"mutation":""},{"gene":"TOMM22","log2":-0.3690578144,"sampleID":"TCGA-B8-4622","pvalue":0,"mutation":""},{"gene":"TOMM40L","log2":-0.1757164029,"sampleID":"TCGA-B8-4622","pvalue":0,"mutation":""},{"gene":"TOMM40","log2":0.2480225251,"sampleID":"TCGA-B8-4622","pvalue":0,"mutation":""},{"gene":"TOMM5","log2":-1.6090194778,"sampleID":"TCGA-B8-4622","pvalue":0,"mutation":""},{"gene":"TOMM6","log2":-0.514698719,"sampleID":"TCGA-B8-4622","pvalue":0,"mutation":""},{"gene":"TOMM70A","log2":0.2675619567,"sampleID":"TCGA-B8-4622","pvalue":0,"mutation":""},{"gene":"TOMM7","log2":0.5134882361,"sampleID":"TCGA-B8-4622","pvalue":0,"mutation":""},{"gene":"TOP1MT","log2":0.5265691304,"sampleID":"TCGA-B8-4622","pvalue":0,"mutation":""},{"gene":"TOP3A","log2":1.417469573,"sampleID":"TCGA-B8-4622","pvalue":0,"mutation":""},{"gene":"TP53","log2":0.4196932678,"sampleID":"TCGA-B8-4622","pvalue":0,"mutation":""},{"gene":"TPI1","log2":1.7762719359,"sampleID":"TCGA-B8-4622","pvalue":0,"mutation":""},{"gene":"TRAK1","log2":0.2019303087,"sampleID":"TCGA-B8-4622","pvalue":0,"mutation":""},{"gene":"TRAK2","log2":-0.1298787112,"sampleID":"TCGA-B8-4622","pvalue":0,"mutation":""},{"gene":"TRAP1","log2":0.0762869165,"sampleID":"TCGA-B8-4622","pvalue":0,"mutation":""},{"gene":"TRIT1","log2":0.967669266,"sampleID":"TCGA-B8-4622","pvalue":0,"mutation":""},{"gene":"TRMT112","log2":0.0996645778,"sampleID":"TCGA-B8-4622","pvalue":0,"mutation":""},{"gene":"TRMT11","log2":0.1065863102,"sampleID":"TCGA-B8-4622","pvalue":0,"mutation":""},{"gene":"TRMT1","log2":1.4423874959,"sampleID":"TCGA-B8-4622","pvalue":0,"mutation":""},{"gene":"TRMT2B","log2":0.324967995,"sampleID":"TCGA-B8-4622","pvalue":0,"mutation":""},{"gene":"TRMT5","log2":-0.1301537945,"sampleID":"TCGA-B8-4622","pvalue":0,"mutation":""},{"gene":"TRMT61B","log2":-0.3635839165,"sampleID":"TCGA-B8-4622","pvalue":0,"mutation":""},{"gene":"TRMT6","log2":-0.3495540148,"sampleID":"TCGA-B8-4622","pvalue":0,"mutation":""},{"gene":"TRMU","log2":0.596334516,"sampleID":"TCGA-B8-4622","pvalue":0,"mutation":""},{"gene":"TRNT1","log2":-0.5649211622,"sampleID":"TCGA-B8-4622","pvalue":0,"mutation":""},{"gene":"TRUB2","log2":-1.0190329723,"sampleID":"TCGA-B8-4622","pvalue":0,"mutation":""},{"gene":"TSFM","log2":-0.1842230247,"sampleID":"TCGA-B8-4622","pvalue":0,"mutation":""},{"gene":"TTC19","log2":-0.0504262416,"sampleID":"TCGA-B8-4622","pvalue":0,"mutation":""},{"gene":"TUFM","log2":-0.4498312409,"sampleID":"TCGA-B8-4622","pvalue":0,"mutation":""},{"gene":"TXN2","log2":-0.3118212919,"sampleID":"TCGA-B8-4622","pvalue":0,"mutation":""},{"gene":"TXNRD2","log2":-0.0246788805,"sampleID":"TCGA-B8-4622","pvalue":0,"mutation":""},{"gene":"UNG","log2":0.5830940324,"sampleID":"TCGA-B8-4622","pvalue":0,"mutation":""},{"gene":"UQCC","log2":0.3556900109,"sampleID":"TCGA-B8-4622","pvalue":0,"mutation":""},{"gene":"UQCR10","log2":-0.4101036535,"sampleID":"TCGA-B8-4622","pvalue":0,"mutation":""},{"gene":"UQCR11","log2":-0.6704837171,"sampleID":"TCGA-B8-4622","pvalue":0,"mutation":""},{"gene":"UQCRB","log2":-0.534578914,"sampleID":"TCGA-B8-4622","pvalue":0,"mutation":""},{"gene":"UQCRC1","log2":-1.3873736915,"sampleID":"TCGA-B8-4622","pvalue":0,"mutation":""},{"gene":"UQCRC2","log2":-0.4834213227,"sampleID":"TCGA-B8-4622","pvalue":0,"mutation":""},{"gene":"UQCRFS1","log2":-1.5416839285,"sampleID":"TCGA-B8-4622","pvalue":0,"mutation":""},{"gene":"UQCRH","log2":-1.1390767695,"sampleID":"TCGA-B8-4622","pvalue":0,"mutation":""},{"gene":"UQCRQ","log2":-1.1249754974,"sampleID":"TCGA-B8-4622","pvalue":0,"mutation":""},{"gene":"UROD","log2":0.3015257845,"sampleID":"TCGA-B8-4622","pvalue":0,"mutation":""},{"gene":"UROS","log2":-0.5798589101,"sampleID":"TCGA-B8-4622","pvalue":0,"mutation":""},{"gene":"VARS2","log2":0.9529333738,"sampleID":"TCGA-B8-4622","pvalue":0,"mutation":""},{"gene":"VDAC1","log2":0.1030522178,"sampleID":"TCGA-B8-4622","pvalue":0,"mutation":""},{"gene":"VDAC2","log2":0.4273388009,"sampleID":"TCGA-B8-4622","pvalue":0,"mutation":""},{"gene":"VDAC3","log2":-0.0203585154,"sampleID":"TCGA-B8-4622","pvalue":0,"mutation":""},{"gene":"WARS2","log2":0.1458269855,"sampleID":"TCGA-B8-4622","pvalue":0,"mutation":""},{"gene":"XIAP","log2":-0.0230459698,"sampleID":"TCGA-B8-4622","pvalue":0,"mutation":""},{"gene":"YARS2","log2":0.4481727492,"sampleID":"TCGA-B8-4622","pvalue":0,"mutation":""},{"gene":"YME1L1","log2":0.237203991,"sampleID":"TCGA-B8-4622","pvalue":0,"mutation":""},{"gene":"YRDC","log2":0.0382869635,"sampleID":"TCGA-B8-4622","pvalue":0,"mutation":""}]