[{"gene":"AARS2","log2":0.4355744157,"sampleID":"TCGA-B0-5703","pvalue":0,"mutation":""},{"gene":"ABCB7","log2":-0.2700007622,"sampleID":"TCGA-B0-5703","pvalue":0,"mutation":""},{"gene":"ACAA2","log2":0.7054607578,"sampleID":"TCGA-B0-5703","pvalue":0,"mutation":""},{"gene":"ACAD10","log2":-0.8017648407,"sampleID":"TCGA-B0-5703","pvalue":0,"mutation":""},{"gene":"ACAD11","log2":1.8939978381,"sampleID":"TCGA-B0-5703","pvalue":0,"mutation":""},{"gene":"ACAD8","log2":-1.1213645668,"sampleID":"TCGA-B0-5703","pvalue":0,"mutation":""},{"gene":"ACAD9","log2":-0.7158827367,"sampleID":"TCGA-B0-5703","pvalue":0,"mutation":""},{"gene":"ACADL","log2":0.3429140291,"sampleID":"TCGA-B0-5703","pvalue":0,"mutation":""},{"gene":"ACADM","log2":-1.8896122374,"sampleID":"TCGA-B0-5703","pvalue":0,"mutation":""},{"gene":"ACADSB","log2":-2.2466549188,"sampleID":"TCGA-B0-5703","pvalue":0,"mutation":""},{"gene":"ACADS","log2":0.0556364602,"sampleID":"TCGA-B0-5703","pvalue":0,"mutation":""},{"gene":"ACADVL","log2":0.0994134316,"sampleID":"TCGA-B0-5703","pvalue":0,"mutation":""},{"gene":"ACO2","log2":-0.2678209971,"sampleID":"TCGA-B0-5703","pvalue":0,"mutation":""},{"gene":"ACSBG1","log2":-0.5575853426,"sampleID":"TCGA-B0-5703","pvalue":0,"mutation":""},{"gene":"ACSBG2","log2":-3.2932505727,"sampleID":"TCGA-B0-5703","pvalue":0,"mutation":""},{"gene":"ACSL1","log2":-0.6462204628,"sampleID":"TCGA-B0-5703","pvalue":0,"mutation":""},{"gene":"ACSL3","log2":-1.0662825419,"sampleID":"TCGA-B0-5703","pvalue":0,"mutation":""},{"gene":"ACSL4","log2":-2.294712728,"sampleID":"TCGA-B0-5703","pvalue":0,"mutation":""},{"gene":"ACSL5","log2":-0.839529013,"sampleID":"TCGA-B0-5703","pvalue":0,"mutation":""},{"gene":"ACSL6","log2":-4.548677516,"sampleID":"TCGA-B0-5703","pvalue":0,"mutation":""},{"gene":"ACSM1","log2":-0.3683714285,"sampleID":"TCGA-B0-5703","pvalue":0,"mutation":""},{"gene":"ACSM2A","log2":0.9592324396,"sampleID":"TCGA-B0-5703","pvalue":0,"mutation":""},{"gene":"ACSM2B","log2":1.4834209845,"sampleID":"TCGA-B0-5703","pvalue":0,"mutation":""},{"gene":"ACSM3","log2":-0.7609403065,"sampleID":"TCGA-B0-5703","pvalue":0,"mutation":""},{"gene":"ACSM5","log2":1.5945754668,"sampleID":"TCGA-B0-5703","pvalue":0,"mutation":""},{"gene":"ACSS1","log2":-0.7113602173,"sampleID":"TCGA-B0-5703","pvalue":0,"mutation":""},{"gene":"ACSS2","log2":-0.5704206205,"sampleID":"TCGA-B0-5703","pvalue":0,"mutation":""},{"gene":"ACSS3","log2":-0.7364760295,"sampleID":"TCGA-B0-5703","pvalue":0,"mutation":""},{"gene":"AFG3L2","log2":-0.0967455282,"sampleID":"TCGA-B0-5703","pvalue":0,"mutation":""},{"gene":"AIFM1","log2":-0.6817199153,"sampleID":"TCGA-B0-5703","pvalue":0,"mutation":""},{"gene":"AK3","log2":-1.7944177,"sampleID":"TCGA-B0-5703","pvalue":0,"mutation":""},{"gene":"ALAD","log2":-0.766894381,"sampleID":"TCGA-B0-5703","pvalue":0,"mutation":""},{"gene":"ALAS1","log2":-3.0215744104,"sampleID":"TCGA-B0-5703","pvalue":0,"mutation":""},{"gene":"ALAS2","log2":0.9476168701,"sampleID":"TCGA-B0-5703","pvalue":0,"mutation":""},{"gene":"ALDOA","log2":0.7363467786,"sampleID":"TCGA-B0-5703","pvalue":0,"mutation":""},{"gene":"ALDOB","log2":-2.6055887957,"sampleID":"TCGA-B0-5703","pvalue":0,"mutation":""},{"gene":"ALDOC","log2":1.8936158163,"sampleID":"TCGA-B0-5703","pvalue":0,"mutation":""},{"gene":"AMBRA1","log2":0.2100111484,"sampleID":"TCGA-B0-5703","pvalue":0,"mutation":""},{"gene":"ANP32A","log2":-0.3956003439,"sampleID":"TCGA-B0-5703","pvalue":0,"mutation":""},{"gene":"APAF1","log2":0.3080675852,"sampleID":"TCGA-B0-5703","pvalue":0,"mutation":""},{"gene":"APEX1","log2":0.1658311423,"sampleID":"TCGA-B0-5703","pvalue":0,"mutation":""},{"gene":"APEX2","log2":0.1824095893,"sampleID":"TCGA-B0-5703","pvalue":0,"mutation":""},{"gene":"ARG2","log2":-5.1985432264,"sampleID":"TCGA-B0-5703","pvalue":0,"mutation":""},{"gene":"ASL","log2":0.2405541137,"sampleID":"TCGA-B0-5703","pvalue":0,"mutation":""},{"gene":"ASS1","log2":-1.0744999818,"sampleID":"TCGA-B0-5703","pvalue":0,"mutation":""},{"gene":"ATAD3A","log2":-0.2434735241,"sampleID":"TCGA-B0-5703","pvalue":0,"mutation":""},{"gene":"ATAD3B","log2":-0.379982986,"sampleID":"TCGA-B0-5703","pvalue":0,"mutation":""},{"gene":"ATP5A1","log2":-1.6529282257,"sampleID":"TCGA-B0-5703","pvalue":0,"mutation":""},{"gene":"ATP5B","log2":-1.4292457637,"sampleID":"TCGA-B0-5703","pvalue":0,"mutation":""},{"gene":"ATP5C1","log2":-1.4113342169,"sampleID":"TCGA-B0-5703","pvalue":0,"mutation":""},{"gene":"ATP5D","log2":0.1388719422,"sampleID":"TCGA-B0-5703","pvalue":0,"mutation":""},{"gene":"ATP5E","log2":-1.2734228452,"sampleID":"TCGA-B0-5703","pvalue":0,"mutation":""},{"gene":"ATP5F1","log2":-1.8712711979,"sampleID":"TCGA-B0-5703","pvalue":0,"mutation":""},{"gene":"ATP5G1","log2":-1.6637027613,"sampleID":"TCGA-B0-5703","pvalue":0,"mutation":""},{"gene":"ATP5G2","log2":-0.056095873,"sampleID":"TCGA-B0-5703","pvalue":0,"mutation":""},{"gene":"ATP5G3","log2":-1.5444692118,"sampleID":"TCGA-B0-5703","pvalue":0,"mutation":""},{"gene":"ATP5H","log2":-0.9449638522,"sampleID":"TCGA-B0-5703","pvalue":0,"mutation":""},{"gene":"ATP5I","log2":-1.0548599202,"sampleID":"TCGA-B0-5703","pvalue":0,"mutation":""},{"gene":"ATP5J2","log2":-0.9827577321,"sampleID":"TCGA-B0-5703","pvalue":0,"mutation":""},{"gene":"ATP5J","log2":-1.7713002588,"sampleID":"TCGA-B0-5703","pvalue":0,"mutation":""},{"gene":"ATP5L","log2":-1.5562924039,"sampleID":"TCGA-B0-5703","pvalue":0,"mutation":""},{"gene":"ATP5O","log2":-1.1256769026,"sampleID":"TCGA-B0-5703","pvalue":0,"mutation":""},{"gene":"ATPAF1","log2":-2.1601811848,"sampleID":"TCGA-B0-5703","pvalue":0,"mutation":""},{"gene":"ATPAF2","log2":-0.2755653645,"sampleID":"TCGA-B0-5703","pvalue":0,"mutation":""},{"gene":"ATPIF1","log2":-2.6406240426,"sampleID":"TCGA-B0-5703","pvalue":0,"mutation":""},{"gene":"BAD","log2":-0.0677365961,"sampleID":"TCGA-B0-5703","pvalue":0,"mutation":""},{"gene":"BAK1","log2":-0.374542622,"sampleID":"TCGA-B0-5703","pvalue":0,"mutation":""},{"gene":"BAX","log2":0.9156439313,"sampleID":"TCGA-B0-5703","pvalue":0,"mutation":""},{"gene":"BBC3","log2":1.4483638159,"sampleID":"TCGA-B0-5703","pvalue":0,"mutation":""},{"gene":"BCKDHA","log2":-0.4827302895,"sampleID":"TCGA-B0-5703","pvalue":0,"mutation":""},{"gene":"BCKDHB","log2":-1.6003395266,"sampleID":"TCGA-B0-5703","pvalue":0,"mutation":""},{"gene":"BCL2L11","log2":-0.1429387073,"sampleID":"TCGA-B0-5703","pvalue":0,"mutation":""},{"gene":"BCL2L1","log2":0.2000998891,"sampleID":"TCGA-B0-5703","pvalue":0,"mutation":""},{"gene":"BCL2","log2":1.4329192916,"sampleID":"TCGA-B0-5703","pvalue":0,"mutation":""},{"gene":"BCS1L","log2":-0.2141588801,"sampleID":"TCGA-B0-5703","pvalue":0,"mutation":""},{"gene":"BECN1","log2":-0.9190658774,"sampleID":"TCGA-B0-5703","pvalue":0,"mutation":""},{"gene":"BID","log2":1.1221125909,"sampleID":"TCGA-B0-5703","pvalue":0,"mutation":""},{"gene":"BIK","log2":-3.5844586601,"sampleID":"TCGA-B0-5703","pvalue":0,"mutation":""},{"gene":"BNIP3L","log2":0.7859723714,"sampleID":"TCGA-B0-5703","pvalue":0,"mutation":""},{"gene":"BNIP3","log2":0.4061036355,"sampleID":"TCGA-B0-5703","pvalue":0,"mutation":""},{"gene":"BOLA3","log2":-0.4789400921,"sampleID":"TCGA-B0-5703","pvalue":0,"mutation":""},{"gene":"BRP44L","log2":-3.0369954529,"sampleID":"TCGA-B0-5703","pvalue":0,"mutation":""},{"gene":"BRP44","log2":-0.8700211376,"sampleID":"TCGA-B0-5703","pvalue":0,"mutation":""},{"gene":"C10orf2","log2":0.4527974756,"sampleID":"TCGA-B0-5703","pvalue":0,"mutation":""},{"gene":"C1orf31","log2":-1.0165402974,"sampleID":"TCGA-B0-5703","pvalue":0,"mutation":""},{"gene":"C20orf7","log2":-1.3576940649,"sampleID":"TCGA-B0-5703","pvalue":0,"mutation":""},{"gene":"C22orf32","log2":-1.2868483262,"sampleID":"TCGA-B0-5703","pvalue":0,"mutation":""},{"gene":"C2orf56","log2":-0.8692307409,"sampleID":"TCGA-B0-5703","pvalue":0,"mutation":""},{"gene":"C7orf44","log2":-0.2627248584,"sampleID":"TCGA-B0-5703","pvalue":0,"mutation":""},{"gene":"C8orf38","log2":-1.145538247,"sampleID":"TCGA-B0-5703","pvalue":0,"mutation":""},{"gene":"CARS2","log2":-0.1658810708,"sampleID":"TCGA-B0-5703","pvalue":0,"mutation":""},{"gene":"CASP3","log2":0.1249866106,"sampleID":"TCGA-B0-5703","pvalue":0,"mutation":""},{"gene":"CASP7","log2":-0.6385798789,"sampleID":"TCGA-B0-5703","pvalue":0,"mutation":""},{"gene":"CASP9","log2":-2.3479638325,"sampleID":"TCGA-B0-5703","pvalue":0,"mutation":""},{"gene":"CCDC109B","log2":0.6083524478,"sampleID":"TCGA-B0-5703","pvalue":0,"mutation":""},{"gene":"CCDC56","log2":-1.0539458041,"sampleID":"TCGA-B0-5703","pvalue":0,"mutation":""},{"gene":"CCDC90A","log2":-0.6161179577,"sampleID":"TCGA-B0-5703","pvalue":0,"mutation":""},{"gene":"CD36","log2":2.3643368341,"sampleID":"TCGA-B0-5703","pvalue":0,"mutation":""},{"gene":"CDK1","log2":0.0136994907,"sampleID":"TCGA-B0-5703","pvalue":0,"mutation":""},{"gene":"CDK5RAP1","log2":-0.556490601,"sampleID":"TCGA-B0-5703","pvalue":0,"mutation":""},{"gene":"CDKAL1","log2":0.0509410764,"sampleID":"TCGA-B0-5703","pvalue":0,"mutation":""},{"gene":"CDS1","log2":-2.2260603213,"sampleID":"TCGA-B0-5703","pvalue":0,"mutation":""},{"gene":"CHCHD4","log2":-1.1119033835,"sampleID":"TCGA-B0-5703","pvalue":0,"mutation":""},{"gene":"CHCHD8","log2":0.2125020695,"sampleID":"TCGA-B0-5703","pvalue":0,"mutation":""},{"gene":"CIAO1","log2":-0.3949360389,"sampleID":"TCGA-B0-5703","pvalue":0,"mutation":""},{"gene":"CIAPIN1","log2":-0.4758202772,"sampleID":"TCGA-B0-5703","pvalue":0,"mutation":""},{"gene":"CLPP","log2":-0.1282285093,"sampleID":"TCGA-B0-5703","pvalue":0,"mutation":""},{"gene":"CLPX","log2":-0.8368945324,"sampleID":"TCGA-B0-5703","pvalue":0,"mutation":""},{"gene":"CMPK2","log2":0.0945962374,"sampleID":"TCGA-B0-5703","pvalue":0,"mutation":""},{"gene":"COX10","log2":-0.5521408013,"sampleID":"TCGA-B0-5703","pvalue":0,"mutation":""},{"gene":"COX11","log2":-0.8879747641,"sampleID":"TCGA-B0-5703","pvalue":0,"mutation":""},{"gene":"COX15","log2":-1.2615267556,"sampleID":"TCGA-B0-5703","pvalue":0,"mutation":""},{"gene":"COX17","log2":-1.7006494666,"sampleID":"TCGA-B0-5703","pvalue":0,"mutation":""},{"gene":"COX18","log2":-0.9462125542,"sampleID":"TCGA-B0-5703","pvalue":0,"mutation":""},{"gene":"COX19","log2":0.4186032521,"sampleID":"TCGA-B0-5703","pvalue":0,"mutation":""},{"gene":"COX4I1","log2":-1.2447038602,"sampleID":"TCGA-B0-5703","pvalue":0,"mutation":""},{"gene":"COX4I2","log2":3.0305783818,"sampleID":"TCGA-B0-5703","pvalue":0,"mutation":""},{"gene":"COX5A","log2":-1.4722566263,"sampleID":"TCGA-B0-5703","pvalue":0,"mutation":""},{"gene":"COX5B","log2":-1.3582031856,"sampleID":"TCGA-B0-5703","pvalue":0,"mutation":""},{"gene":"COX6A1","log2":-1.1422397817,"sampleID":"TCGA-B0-5703","pvalue":0,"mutation":""},{"gene":"COX6A2","log2":-0.3823764404,"sampleID":"TCGA-B0-5703","pvalue":0,"mutation":""},{"gene":"COX6B1","log2":-1.2622820959,"sampleID":"TCGA-B0-5703","pvalue":0,"mutation":""},{"gene":"COX6C","log2":-0.6226528222,"sampleID":"TCGA-B0-5703","pvalue":0,"mutation":""},{"gene":"COX7A1","log2":-2.0095687931,"sampleID":"TCGA-B0-5703","pvalue":0,"mutation":""},{"gene":"COX7A2","log2":-1.3324125854,"sampleID":"TCGA-B0-5703","pvalue":0,"mutation":""},{"gene":"COX7B","log2":-2.1203430481,"sampleID":"TCGA-B0-5703","pvalue":0,"mutation":""},{"gene":"COX7C","log2":-1.1687134981,"sampleID":"TCGA-B0-5703","pvalue":0,"mutation":""},{"gene":"COX8A","log2":-1.2545812323,"sampleID":"TCGA-B0-5703","pvalue":0,"mutation":""},{"gene":"CPOX","log2":-0.0886731711,"sampleID":"TCGA-B0-5703","pvalue":0,"mutation":""},{"gene":"CPS1","log2":-2.6046757025,"sampleID":"TCGA-B0-5703","pvalue":0,"mutation":""},{"gene":"CPT1A","log2":-0.7569727041,"sampleID":"TCGA-B0-5703","pvalue":0,"mutation":""},{"gene":"CPT1B","log2":-0.9289542308,"sampleID":"TCGA-B0-5703","pvalue":0,"mutation":""},{"gene":"CPT1C","log2":-0.3735358166,"sampleID":"TCGA-B0-5703","pvalue":0,"mutation":""},{"gene":"CPT2","log2":-0.730974758,"sampleID":"TCGA-B0-5703","pvalue":0,"mutation":""},{"gene":"CRAT","log2":1.1104494397,"sampleID":"TCGA-B0-5703","pvalue":0,"mutation":""},{"gene":"CREB1","log2":0.0378143161,"sampleID":"TCGA-B0-5703","pvalue":0,"mutation":""},{"gene":"CRLS1","log2":-0.8441244247,"sampleID":"TCGA-B0-5703","pvalue":0,"mutation":""},{"gene":"CS","log2":-0.3660697552,"sampleID":"TCGA-B0-5703","pvalue":0,"mutation":""},{"gene":"CYC1","log2":0.0376107449,"sampleID":"TCGA-B0-5703","pvalue":0,"mutation":""},{"gene":"CYCS","log2":-0.9411144054,"sampleID":"TCGA-B0-5703","pvalue":0,"mutation":""},{"gene":"DAP3","log2":-0.5227560126,"sampleID":"TCGA-B0-5703","pvalue":0,"mutation":""},{"gene":"DARS2","log2":-0.2826655626,"sampleID":"TCGA-B0-5703","pvalue":0,"mutation":""},{"gene":"DDX28","log2":-0.1189035056,"sampleID":"TCGA-B0-5703","pvalue":0,"mutation":""},{"gene":"DECR1","log2":-1.2047204423,"sampleID":"TCGA-B0-5703","pvalue":0,"mutation":""},{"gene":"DHX30","log2":-0.6298653319,"sampleID":"TCGA-B0-5703","pvalue":0,"mutation":""},{"gene":"DIABLO","log2":-0.1347472755,"sampleID":"TCGA-B0-5703","pvalue":0,"mutation":""},{"gene":"DLAT","log2":-0.9993873806,"sampleID":"TCGA-B0-5703","pvalue":0,"mutation":""},{"gene":"DLD","log2":-1.0477189712,"sampleID":"TCGA-B0-5703","pvalue":0,"mutation":""},{"gene":"DLST","log2":-0.6150359239,"sampleID":"TCGA-B0-5703","pvalue":0,"mutation":""},{"gene":"DNAJC19","log2":-1.4721445917,"sampleID":"TCGA-B0-5703","pvalue":0,"mutation":""},{"gene":"DNM1L","log2":-1.0405497992,"sampleID":"TCGA-B0-5703","pvalue":0,"mutation":""},{"gene":"DNM1","log2":2.127084446,"sampleID":"TCGA-B0-5703","pvalue":0,"mutation":""},{"gene":"DUS2L","log2":0.1300761769,"sampleID":"TCGA-B0-5703","pvalue":0,"mutation":""},{"gene":"DYNLL1","log2":-0.4444009002,"sampleID":"TCGA-B0-5703","pvalue":0,"mutation":""},{"gene":"EARS2","log2":0.4424455084,"sampleID":"TCGA-B0-5703","pvalue":0,"mutation":""},{"gene":"ECHS1","log2":-1.8602321759,"sampleID":"TCGA-B0-5703","pvalue":0,"mutation":""},{"gene":"ECSIT","log2":0.3764727616,"sampleID":"TCGA-B0-5703","pvalue":0,"mutation":""},{"gene":"EFHA1","log2":-1.5171273631,"sampleID":"TCGA-B0-5703","pvalue":0,"mutation":""},{"gene":"EFHA2","log2":-0.466793968,"sampleID":"TCGA-B0-5703","pvalue":0,"mutation":""},{"gene":"EIF3M","log2":-0.3314434755,"sampleID":"TCGA-B0-5703","pvalue":0,"mutation":""},{"gene":"ELAC2","log2":0.1650703137,"sampleID":"TCGA-B0-5703","pvalue":0,"mutation":""},{"gene":"ENDOG","log2":-0.6419399689,"sampleID":"TCGA-B0-5703","pvalue":0,"mutation":""},{"gene":"ENO1","log2":-0.1920958763,"sampleID":"TCGA-B0-5703","pvalue":0,"mutation":""},{"gene":"ENO2","log2":1.4978633356,"sampleID":"TCGA-B0-5703","pvalue":0,"mutation":""},{"gene":"ENO3","log2":-0.4499022121,"sampleID":"TCGA-B0-5703","pvalue":0,"mutation":""},{"gene":"FABP1","log2":-6.7054444357,"sampleID":"TCGA-B0-5703","pvalue":0,"mutation":""},{"gene":"FABP3","log2":-0.9800355015,"sampleID":"TCGA-B0-5703","pvalue":0,"mutation":""},{"gene":"FABP4","log2":-0.9856438934,"sampleID":"TCGA-B0-5703","pvalue":0,"mutation":""},{"gene":"FABP5","log2":-1.1426333985,"sampleID":"TCGA-B0-5703","pvalue":0,"mutation":""},{"gene":"FABP6","log2":8.5718884975,"sampleID":"TCGA-B0-5703","pvalue":0,"mutation":""},{"gene":"FAM96A","log2":-0.8078625525,"sampleID":"TCGA-B0-5703","pvalue":0,"mutation":""},{"gene":"FAM96B","log2":-0.0434099724,"sampleID":"TCGA-B0-5703","pvalue":0,"mutation":""},{"gene":"FARS2","log2":-0.1951785903,"sampleID":"TCGA-B0-5703","pvalue":0,"mutation":""},{"gene":"FDX1L","log2":-0.7050806915,"sampleID":"TCGA-B0-5703","pvalue":0,"mutation":""},{"gene":"FDX1","log2":-1.2616805331,"sampleID":"TCGA-B0-5703","pvalue":0,"mutation":""},{"gene":"FDXR","log2":1.4266411486,"sampleID":"TCGA-B0-5703","pvalue":0,"mutation":""},{"gene":"FECH","log2":-2.4410736917,"sampleID":"TCGA-B0-5703","pvalue":0,"mutation":""},{"gene":"FH","log2":-1.8077853193,"sampleID":"TCGA-B0-5703","pvalue":0,"mutation":""},{"gene":"FIS1","log2":-0.2636326833,"sampleID":"TCGA-B0-5703","pvalue":0,"mutation":""},{"gene":"FOXRED1","log2":-0.6004008445,"sampleID":"TCGA-B0-5703","pvalue":0,"mutation":""},{"gene":"FXN","log2":-0.8206517013,"sampleID":"TCGA-B0-5703","pvalue":0,"mutation":""},{"gene":"GABARAP","log2":-0.8496628667,"sampleID":"TCGA-B0-5703","pvalue":0,"mutation":""},{"gene":"GAPDHS","log2":-2.0079773254,"sampleID":"TCGA-B0-5703","pvalue":0,"mutation":""},{"gene":"GAPDH","log2":0.9456302231,"sampleID":"TCGA-B0-5703","pvalue":0,"mutation":""},{"gene":"GARS","log2":0.4538378599,"sampleID":"TCGA-B0-5703","pvalue":0,"mutation":""},{"gene":"GATC","log2":-1.1655901179,"sampleID":"TCGA-B0-5703","pvalue":0,"mutation":""},{"gene":"GCK","log2":-2.1916093483,"sampleID":"TCGA-B0-5703","pvalue":0,"mutation":""},{"gene":"GCLC","log2":0.6802619026,"sampleID":"TCGA-B0-5703","pvalue":0,"mutation":""},{"gene":"GCLM","log2":-0.5006022369,"sampleID":"TCGA-B0-5703","pvalue":0,"mutation":""},{"gene":"GDAP1","log2":-1.0832122816,"sampleID":"TCGA-B0-5703","pvalue":0,"mutation":""},{"gene":"GFER","log2":0.2740440845,"sampleID":"TCGA-B0-5703","pvalue":0,"mutation":""},{"gene":"GFM1","log2":-0.5564948421,"sampleID":"TCGA-B0-5703","pvalue":0,"mutation":""},{"gene":"GFM2","log2":-0.6123641709,"sampleID":"TCGA-B0-5703","pvalue":0,"mutation":""},{"gene":"GLRX2","log2":-0.0829828378,"sampleID":"TCGA-B0-5703","pvalue":0,"mutation":""},{"gene":"GLRX5","log2":-1.5553731213,"sampleID":"TCGA-B0-5703","pvalue":0,"mutation":""},{"gene":"GOT2","log2":-1.365040203,"sampleID":"TCGA-B0-5703","pvalue":0,"mutation":""},{"gene":"GPI","log2":0.1155990313,"sampleID":"TCGA-B0-5703","pvalue":0,"mutation":""},{"gene":"GPX1","log2":-0.7069075751,"sampleID":"TCGA-B0-5703","pvalue":0,"mutation":""},{"gene":"GPX4","log2":-0.0094282413,"sampleID":"TCGA-B0-5703","pvalue":0,"mutation":""},{"gene":"GRPEL1","log2":-0.1939879869,"sampleID":"TCGA-B0-5703","pvalue":0,"mutation":""},{"gene":"GRPEL2","log2":-0.1392405933,"sampleID":"TCGA-B0-5703","pvalue":0,"mutation":""},{"gene":"GSR","log2":-0.6891109225,"sampleID":"TCGA-B0-5703","pvalue":0,"mutation":""},{"gene":"GSS","log2":-0.270438654,"sampleID":"TCGA-B0-5703","pvalue":0,"mutation":""},{"gene":"GSTA1","log2":-2.1588738536,"sampleID":"TCGA-B0-5703","pvalue":0,"mutation":""},{"gene":"GSTA2","log2":-3.631710789,"sampleID":"TCGA-B0-5703","pvalue":0,"mutation":""},{"gene":"GSTA4","log2":-0.7333207511,"sampleID":"TCGA-B0-5703","pvalue":0,"mutation":""},{"gene":"GSTP1","log2":-1.3668760418,"sampleID":"TCGA-B0-5703","pvalue":0,"mutation":""},{"gene":"GTPBP3","log2":0.5194571752,"sampleID":"TCGA-B0-5703","pvalue":0,"mutation":""},{"gene":"HADHA","log2":-0.0323588485,"sampleID":"TCGA-B0-5703","pvalue":0,"mutation":""},{"gene":"HADHB","log2":-0.835523215,"sampleID":"TCGA-B0-5703","pvalue":0,"mutation":""},{"gene":"HADH","log2":-1.0401385243,"sampleID":"TCGA-B0-5703","pvalue":0,"mutation":""},{"gene":"HARS2","log2":-0.4266998758,"sampleID":"TCGA-B0-5703","pvalue":0,"mutation":""},{"gene":"HCCS","log2":-1.090801326,"sampleID":"TCGA-B0-5703","pvalue":0,"mutation":""},{"gene":"HK1","log2":-0.7073929589,"sampleID":"TCGA-B0-5703","pvalue":0,"mutation":""},{"gene":"HK2","log2":3.8759529515,"sampleID":"TCGA-B0-5703","pvalue":0,"mutation":""},{"gene":"HK3","log2":1.4909476712,"sampleID":"TCGA-B0-5703","pvalue":0,"mutation":""},{"gene":"HMBS","log2":-0.1062352247,"sampleID":"TCGA-B0-5703","pvalue":0,"mutation":""},{"gene":"HSCB","log2":-0.3238904333,"sampleID":"TCGA-B0-5703","pvalue":0,"mutation":""},{"gene":"HSD17B10","log2":-0.8174012639,"sampleID":"TCGA-B0-5703","pvalue":0,"mutation":""},{"gene":"HSPA9","log2":-0.1430398848,"sampleID":"TCGA-B0-5703","pvalue":0,"mutation":""},{"gene":"HTRA2","log2":0.0772215203,"sampleID":"TCGA-B0-5703","pvalue":0,"mutation":""},{"gene":"IARS2","log2":-0.9358918196,"sampleID":"TCGA-B0-5703","pvalue":0,"mutation":""},{"gene":"IDH1","log2":-0.303906436,"sampleID":"TCGA-B0-5703","pvalue":0,"mutation":""},{"gene":"IDH2","log2":-1.2649994839,"sampleID":"TCGA-B0-5703","pvalue":0,"mutation":""},{"gene":"IDH3A","log2":-0.9444727396,"sampleID":"TCGA-B0-5703","pvalue":0,"mutation":""},{"gene":"IDH3B","log2":-0.2743761092,"sampleID":"TCGA-B0-5703","pvalue":0,"mutation":""},{"gene":"IDH3G","log2":-0.7996092819,"sampleID":"TCGA-B0-5703","pvalue":0,"mutation":""},{"gene":"IMMP1L","log2":-1.1342907953,"sampleID":"TCGA-B0-5703","pvalue":0,"mutation":""},{"gene":"IMMP2L","log2":-0.400455512,"sampleID":"TCGA-B0-5703","pvalue":0,"mutation":""},{"gene":"ISCA1","log2":-0.9906742081,"sampleID":"TCGA-B0-5703","pvalue":0,"mutation":""},{"gene":"ISCA2","log2":-0.7150349532,"sampleID":"TCGA-B0-5703","pvalue":0,"mutation":""},{"gene":"ISCU","log2":-1.245400007,"sampleID":"TCGA-B0-5703","pvalue":0,"mutation":""},{"gene":"ITPR1","log2":-1.0657955564,"sampleID":"TCGA-B0-5703","pvalue":0,"mutation":""},{"gene":"ITPR2","log2":-0.9658815585,"sampleID":"TCGA-B0-5703","pvalue":0,"mutation":""},{"gene":"ITPR3","log2":0.5344483901,"sampleID":"TCGA-B0-5703","pvalue":0,"mutation":""},{"gene":"KARS","log2":-0.1523851098,"sampleID":"TCGA-B0-5703","pvalue":0,"mutation":""},{"gene":"KIAA0391","log2":-0.3901472167,"sampleID":"TCGA-B0-5703","pvalue":0,"mutation":""},{"gene":"KIF1B","log2":-0.3028420962,"sampleID":"TCGA-B0-5703","pvalue":0,"mutation":""},{"gene":"KIF5B","log2":-0.5203014316,"sampleID":"TCGA-B0-5703","pvalue":0,"mutation":""},{"gene":"LARS2","log2":-1.3756055031,"sampleID":"TCGA-B0-5703","pvalue":0,"mutation":""},{"gene":"LDHAL6B","log2":-1.9791705045,"sampleID":"TCGA-B0-5703","pvalue":0,"mutation":""},{"gene":"LDHA","log2":1.243770145,"sampleID":"TCGA-B0-5703","pvalue":0,"mutation":""},{"gene":"LDHB","log2":-1.7470862769,"sampleID":"TCGA-B0-5703","pvalue":0,"mutation":""},{"gene":"LDHC","log2":-0.8215427168,"sampleID":"TCGA-B0-5703","pvalue":0,"mutation":""},{"gene":"LETM1","log2":0.0342404383,"sampleID":"TCGA-B0-5703","pvalue":0,"mutation":""},{"gene":"LIG3","log2":0.34371169,"sampleID":"TCGA-B0-5703","pvalue":0,"mutation":""},{"gene":"LONP1","log2":0.7657138336,"sampleID":"TCGA-B0-5703","pvalue":0,"mutation":""},{"gene":"LRPPRC","log2":0.0086162666,"sampleID":"TCGA-B0-5703","pvalue":0,"mutation":""},{"gene":"LYRM4","log2":-0.0950418119,"sampleID":"TCGA-B0-5703","pvalue":0,"mutation":""},{"gene":"MAP1LC3A","log2":-2.2676209705,"sampleID":"TCGA-B0-5703","pvalue":0,"mutation":""},{"gene":"MAPK1","log2":0.9064721807,"sampleID":"TCGA-B0-5703","pvalue":0,"mutation":""},{"gene":"MAPK3","log2":-0.1466057521,"sampleID":"TCGA-B0-5703","pvalue":0,"mutation":""},{"gene":"MARCH5","log2":-1.6999962765,"sampleID":"TCGA-B0-5703","pvalue":0,"mutation":""},{"gene":"MARS2","log2":0.9908485268,"sampleID":"TCGA-B0-5703","pvalue":0,"mutation":""},{"gene":"MCL1","log2":-0.1583286104,"sampleID":"TCGA-B0-5703","pvalue":0,"mutation":""},{"gene":"MDH2","log2":-0.0729932048,"sampleID":"TCGA-B0-5703","pvalue":0,"mutation":""},{"gene":"MFF","log2":-1.0794683688,"sampleID":"TCGA-B0-5703","pvalue":0,"mutation":""},{"gene":"MFN1","log2":-0.5500958006,"sampleID":"TCGA-B0-5703","pvalue":0,"mutation":""},{"gene":"MFN2","log2":-1.0763302177,"sampleID":"TCGA-B0-5703","pvalue":0,"mutation":""},{"gene":"MIPEP","log2":-0.9984707101,"sampleID":"TCGA-B0-5703","pvalue":0,"mutation":""},{"gene":"MMS19","log2":-1.1066232822,"sampleID":"TCGA-B0-5703","pvalue":0,"mutation":""},{"gene":"MPV17L2","log2":-0.9442716608,"sampleID":"TCGA-B0-5703","pvalue":0,"mutation":""},{"gene":"MPV17L","log2":-0.2417761229,"sampleID":"TCGA-B0-5703","pvalue":0,"mutation":""},{"gene":"MPV17","log2":0.295720248,"sampleID":"TCGA-B0-5703","pvalue":0,"mutation":""},{"gene":"MRPL10","log2":0.1224147465,"sampleID":"TCGA-B0-5703","pvalue":0,"mutation":""},{"gene":"MRPL11","log2":-0.2207495384,"sampleID":"TCGA-B0-5703","pvalue":0,"mutation":""},{"gene":"MRPL12","log2":-0.3383867961,"sampleID":"TCGA-B0-5703","pvalue":0,"mutation":""},{"gene":"MRPL13","log2":-0.7430645197,"sampleID":"TCGA-B0-5703","pvalue":0,"mutation":""},{"gene":"MRPL14","log2":0.2095842495,"sampleID":"TCGA-B0-5703","pvalue":0,"mutation":""},{"gene":"MRPL15","log2":-0.6843488067,"sampleID":"TCGA-B0-5703","pvalue":0,"mutation":""},{"gene":"MRPL16","log2":-0.8459904269,"sampleID":"TCGA-B0-5703","pvalue":0,"mutation":""},{"gene":"MRPL17","log2":-0.2904644222,"sampleID":"TCGA-B0-5703","pvalue":0,"mutation":""},{"gene":"MRPL18","log2":-0.0265973954,"sampleID":"TCGA-B0-5703","pvalue":0,"mutation":""},{"gene":"MRPL19","log2":-1.1578228972,"sampleID":"TCGA-B0-5703","pvalue":0,"mutation":""},{"gene":"MRPL1","log2":-0.882552419,"sampleID":"TCGA-B0-5703","pvalue":0,"mutation":""},{"gene":"MRPL20","log2":-1.294405068,"sampleID":"TCGA-B0-5703","pvalue":0,"mutation":""},{"gene":"MRPL21","log2":-0.7048989036,"sampleID":"TCGA-B0-5703","pvalue":0,"mutation":""},{"gene":"MRPL22","log2":-0.4163643477,"sampleID":"TCGA-B0-5703","pvalue":0,"mutation":""},{"gene":"MRPL23","log2":0.6751466147,"sampleID":"TCGA-B0-5703","pvalue":0,"mutation":""},{"gene":"MRPL24","log2":-0.0401238611,"sampleID":"TCGA-B0-5703","pvalue":0,"mutation":""},{"gene":"MRPL27","log2":-0.4297346107,"sampleID":"TCGA-B0-5703","pvalue":0,"mutation":""},{"gene":"MRPL28","log2":-0.1710095122,"sampleID":"TCGA-B0-5703","pvalue":0,"mutation":""},{"gene":"MRPL2","log2":-0.5733005732,"sampleID":"TCGA-B0-5703","pvalue":0,"mutation":""},{"gene":"MRPL30","log2":-0.6563960428,"sampleID":"TCGA-B0-5703","pvalue":0,"mutation":""},{"gene":"MRPL32","log2":0.0058019849,"sampleID":"TCGA-B0-5703","pvalue":0,"mutation":""},{"gene":"MRPL33","log2":-2.4367908773,"sampleID":"TCGA-B0-5703","pvalue":0,"mutation":""},{"gene":"MRPL35","log2":-0.6801501595,"sampleID":"TCGA-B0-5703","pvalue":0,"mutation":""},{"gene":"MRPL36","log2":-0.7883999329,"sampleID":"TCGA-B0-5703","pvalue":0,"mutation":""},{"gene":"MRPL37","log2":-0.7508997298,"sampleID":"TCGA-B0-5703","pvalue":0,"mutation":""},{"gene":"MRPL38","log2":-0.4259852402,"sampleID":"TCGA-B0-5703","pvalue":0,"mutation":""},{"gene":"MRPL39","log2":-0.4998390986,"sampleID":"TCGA-B0-5703","pvalue":0,"mutation":""},{"gene":"MRPL3","log2":-1.133342997,"sampleID":"TCGA-B0-5703","pvalue":0,"mutation":""},{"gene":"MRPL40","log2":-0.4298567522,"sampleID":"TCGA-B0-5703","pvalue":0,"mutation":""},{"gene":"MRPL41","log2":-1.1778202989,"sampleID":"TCGA-B0-5703","pvalue":0,"mutation":""},{"gene":"MRPL42","log2":-0.6697779749,"sampleID":"TCGA-B0-5703","pvalue":0,"mutation":""},{"gene":"MRPL43","log2":-1.4005641251,"sampleID":"TCGA-B0-5703","pvalue":0,"mutation":""},{"gene":"MRPL44","log2":-0.3557049316,"sampleID":"TCGA-B0-5703","pvalue":0,"mutation":""},{"gene":"MRPL45","log2":-0.3667973633,"sampleID":"TCGA-B0-5703","pvalue":0,"mutation":""},{"gene":"MRPL46","log2":-0.4943656441,"sampleID":"TCGA-B0-5703","pvalue":0,"mutation":""},{"gene":"MRPL47","log2":-1.084203533,"sampleID":"TCGA-B0-5703","pvalue":0,"mutation":""},{"gene":"MRPL48","log2":-1.0743208783,"sampleID":"TCGA-B0-5703","pvalue":0,"mutation":""},{"gene":"MRPL49","log2":-0.9602072447,"sampleID":"TCGA-B0-5703","pvalue":0,"mutation":""},{"gene":"MRPL4","log2":-0.4598725606,"sampleID":"TCGA-B0-5703","pvalue":0,"mutation":""},{"gene":"MRPL50","log2":0.0063596466,"sampleID":"TCGA-B0-5703","pvalue":0,"mutation":""},{"gene":"MRPL51","log2":-0.4764121522,"sampleID":"TCGA-B0-5703","pvalue":0,"mutation":""},{"gene":"MRPL52","log2":-0.4480905005,"sampleID":"TCGA-B0-5703","pvalue":0,"mutation":""},{"gene":"MRPL53","log2":-0.8377928587,"sampleID":"TCGA-B0-5703","pvalue":0,"mutation":""},{"gene":"MRPL54","log2":-0.7211675288,"sampleID":"TCGA-B0-5703","pvalue":0,"mutation":""},{"gene":"MRPL55","log2":-0.8489314074,"sampleID":"TCGA-B0-5703","pvalue":0,"mutation":""},{"gene":"MRPL9","log2":-0.2158940705,"sampleID":"TCGA-B0-5703","pvalue":0,"mutation":""},{"gene":"MRPS10","log2":-0.7329763532,"sampleID":"TCGA-B0-5703","pvalue":0,"mutation":""},{"gene":"MRPS11","log2":-0.353587666,"sampleID":"TCGA-B0-5703","pvalue":0,"mutation":""},{"gene":"MRPS12","log2":-0.2900897321,"sampleID":"TCGA-B0-5703","pvalue":0,"mutation":""},{"gene":"MRPS14","log2":-0.5983815279,"sampleID":"TCGA-B0-5703","pvalue":0,"mutation":""},{"gene":"MRPS15","log2":-1.2134141298,"sampleID":"TCGA-B0-5703","pvalue":0,"mutation":""},{"gene":"MRPS16","log2":-1.3538261944,"sampleID":"TCGA-B0-5703","pvalue":0,"mutation":""},{"gene":"MRPS17","log2":0.2637756122,"sampleID":"TCGA-B0-5703","pvalue":0,"mutation":""},{"gene":"MRPS18A","log2":-0.1037369434,"sampleID":"TCGA-B0-5703","pvalue":0,"mutation":""},{"gene":"MRPS18B","log2":-0.2094301828,"sampleID":"TCGA-B0-5703","pvalue":0,"mutation":""},{"gene":"MRPS18C","log2":-0.6185811966,"sampleID":"TCGA-B0-5703","pvalue":0,"mutation":""},{"gene":"MRPS21","log2":-0.749247209,"sampleID":"TCGA-B0-5703","pvalue":0,"mutation":""},{"gene":"MRPS22","log2":-0.6575342598,"sampleID":"TCGA-B0-5703","pvalue":0,"mutation":""},{"gene":"MRPS23","log2":-0.3472839936,"sampleID":"TCGA-B0-5703","pvalue":0,"mutation":""},{"gene":"MRPS24","log2":0.0147939845,"sampleID":"TCGA-B0-5703","pvalue":0,"mutation":""},{"gene":"MRPS25","log2":-1.5121653531,"sampleID":"TCGA-B0-5703","pvalue":0,"mutation":""},{"gene":"MRPS26","log2":-0.8931040348,"sampleID":"TCGA-B0-5703","pvalue":0,"mutation":""},{"gene":"MRPS27","log2":-0.4222206197,"sampleID":"TCGA-B0-5703","pvalue":0,"mutation":""},{"gene":"MRPS28","log2":-1.3343606925,"sampleID":"TCGA-B0-5703","pvalue":0,"mutation":""},{"gene":"MRPS2","log2":0.2469705251,"sampleID":"TCGA-B0-5703","pvalue":0,"mutation":""},{"gene":"MRPS30","log2":-0.4985642896,"sampleID":"TCGA-B0-5703","pvalue":0,"mutation":""},{"gene":"MRPS31","log2":-0.5276110103,"sampleID":"TCGA-B0-5703","pvalue":0,"mutation":""},{"gene":"MRPS33","log2":-0.3804357803,"sampleID":"TCGA-B0-5703","pvalue":0,"mutation":""},{"gene":"MRPS34","log2":0.2376997122,"sampleID":"TCGA-B0-5703","pvalue":0,"mutation":""},{"gene":"MRPS35","log2":-0.6587196626,"sampleID":"TCGA-B0-5703","pvalue":0,"mutation":""},{"gene":"MRPS36","log2":-0.5951412871,"sampleID":"TCGA-B0-5703","pvalue":0,"mutation":""},{"gene":"MRPS5","log2":-0.4990140781,"sampleID":"TCGA-B0-5703","pvalue":0,"mutation":""},{"gene":"MRPS6","log2":-2.3874071067,"sampleID":"TCGA-B0-5703","pvalue":0,"mutation":""},{"gene":"MRPS7","log2":-0.678713761,"sampleID":"TCGA-B0-5703","pvalue":0,"mutation":""},{"gene":"MRPS9","log2":-0.8549561633,"sampleID":"TCGA-B0-5703","pvalue":0,"mutation":""},{"gene":"MRRF","log2":-0.3238168534,"sampleID":"TCGA-B0-5703","pvalue":0,"mutation":""},{"gene":"MSTO1","log2":0.5282954685,"sampleID":"TCGA-B0-5703","pvalue":0,"mutation":""},{"gene":"MTFMT","log2":-0.4153223389,"sampleID":"TCGA-B0-5703","pvalue":0,"mutation":""},{"gene":"MTIF2","log2":-0.2742935087,"sampleID":"TCGA-B0-5703","pvalue":0,"mutation":""},{"gene":"MTIF3","log2":-0.5397879216,"sampleID":"TCGA-B0-5703","pvalue":0,"mutation":""},{"gene":"MTO1","log2":-0.1765562758,"sampleID":"TCGA-B0-5703","pvalue":0,"mutation":""},{"gene":"MTPAP","log2":-0.1690674205,"sampleID":"TCGA-B0-5703","pvalue":0,"mutation":""},{"gene":"MTRF1L","log2":-0.5768694214,"sampleID":"TCGA-B0-5703","pvalue":0,"mutation":""},{"gene":"MTRF1","log2":-0.2816316098,"sampleID":"TCGA-B0-5703","pvalue":0,"mutation":""},{"gene":"MUTYH","log2":-0.8193513387,"sampleID":"TCGA-B0-5703","pvalue":0,"mutation":""},{"gene":"NARF","log2":-0.0124009561,"sampleID":"TCGA-B0-5703","pvalue":0,"mutation":""},{"gene":"NARS2","log2":-0.5951703608,"sampleID":"TCGA-B0-5703","pvalue":0,"mutation":""},{"gene":"NDUFA10","log2":-0.6870919765,"sampleID":"TCGA-B0-5703","pvalue":0,"mutation":""},{"gene":"NDUFA11","log2":-0.8739625207,"sampleID":"TCGA-B0-5703","pvalue":0,"mutation":""},{"gene":"NDUFA12","log2":-0.7836015614,"sampleID":"TCGA-B0-5703","pvalue":0,"mutation":""},{"gene":"NDUFA13","log2":-1.1179521857,"sampleID":"TCGA-B0-5703","pvalue":0,"mutation":""},{"gene":"NDUFA1","log2":-1.4323317262,"sampleID":"TCGA-B0-5703","pvalue":0,"mutation":""},{"gene":"NDUFA2","log2":-1.2588288106,"sampleID":"TCGA-B0-5703","pvalue":0,"mutation":""},{"gene":"NDUFA3","log2":-0.8880613029,"sampleID":"TCGA-B0-5703","pvalue":0,"mutation":""},{"gene":"NDUFA4","log2":-2.3008177682,"sampleID":"TCGA-B0-5703","pvalue":0,"mutation":""},{"gene":"NDUFA5","log2":-0.8136138982,"sampleID":"TCGA-B0-5703","pvalue":0,"mutation":""},{"gene":"NDUFA6","log2":-1.5532460422,"sampleID":"TCGA-B0-5703","pvalue":0,"mutation":""},{"gene":"NDUFA7","log2":-0.4379806162,"sampleID":"TCGA-B0-5703","pvalue":0,"mutation":""},{"gene":"NDUFA8","log2":-0.8426328391,"sampleID":"TCGA-B0-5703","pvalue":0,"mutation":""},{"gene":"NDUFA9","log2":-1.0732080543,"sampleID":"TCGA-B0-5703","pvalue":0,"mutation":""},{"gene":"NDUFAB1","log2":-0.8731729018,"sampleID":"TCGA-B0-5703","pvalue":0,"mutation":""},{"gene":"NDUFAF1","log2":-0.4582852764,"sampleID":"TCGA-B0-5703","pvalue":0,"mutation":""},{"gene":"NDUFAF2","log2":-0.3709343044,"sampleID":"TCGA-B0-5703","pvalue":0,"mutation":""},{"gene":"NDUFAF3","log2":-0.7641746931,"sampleID":"TCGA-B0-5703","pvalue":0,"mutation":""},{"gene":"NDUFAF4","log2":-0.6394961874,"sampleID":"TCGA-B0-5703","pvalue":0,"mutation":""},{"gene":"NDUFB10","log2":-0.68471926,"sampleID":"TCGA-B0-5703","pvalue":0,"mutation":""},{"gene":"NDUFB11","log2":-0.3885614287,"sampleID":"TCGA-B0-5703","pvalue":0,"mutation":""},{"gene":"NDUFB1","log2":-1.549184252,"sampleID":"TCGA-B0-5703","pvalue":0,"mutation":""},{"gene":"NDUFB2","log2":-1.2077918585,"sampleID":"TCGA-B0-5703","pvalue":0,"mutation":""},{"gene":"NDUFB3","log2":-1.5367342618,"sampleID":"TCGA-B0-5703","pvalue":0,"mutation":""},{"gene":"NDUFB4","log2":-1.5446020749,"sampleID":"TCGA-B0-5703","pvalue":0,"mutation":""},{"gene":"NDUFB5","log2":-1.4210496872,"sampleID":"TCGA-B0-5703","pvalue":0,"mutation":""},{"gene":"NDUFB6","log2":-0.7828524158,"sampleID":"TCGA-B0-5703","pvalue":0,"mutation":""},{"gene":"NDUFB7","log2":-0.7586667479,"sampleID":"TCGA-B0-5703","pvalue":0,"mutation":""},{"gene":"NDUFB8","log2":-1.5646981824,"sampleID":"TCGA-B0-5703","pvalue":0,"mutation":""},{"gene":"NDUFB9","log2":-1.0599697029,"sampleID":"TCGA-B0-5703","pvalue":0,"mutation":""},{"gene":"NDUFC1","log2":-0.5146910672,"sampleID":"TCGA-B0-5703","pvalue":0,"mutation":""},{"gene":"NDUFC2","log2":-1.6121932163,"sampleID":"TCGA-B0-5703","pvalue":0,"mutation":""},{"gene":"NDUFS1","log2":-1.0239806063,"sampleID":"TCGA-B0-5703","pvalue":0,"mutation":""},{"gene":"NDUFS2","log2":-0.8276128612,"sampleID":"TCGA-B0-5703","pvalue":0,"mutation":""},{"gene":"NDUFS3","log2":-1.2155687279,"sampleID":"TCGA-B0-5703","pvalue":0,"mutation":""},{"gene":"NDUFS4","log2":-1.164941437,"sampleID":"TCGA-B0-5703","pvalue":0,"mutation":""},{"gene":"NDUFS5","log2":-1.5976871392,"sampleID":"TCGA-B0-5703","pvalue":0,"mutation":""},{"gene":"NDUFS6","log2":-0.8278647112,"sampleID":"TCGA-B0-5703","pvalue":0,"mutation":""},{"gene":"NDUFS7","log2":-0.8016601276,"sampleID":"TCGA-B0-5703","pvalue":0,"mutation":""},{"gene":"NDUFS8","log2":-1.4316836812,"sampleID":"TCGA-B0-5703","pvalue":0,"mutation":""},{"gene":"NDUFV1","log2":-1.0497800461,"sampleID":"TCGA-B0-5703","pvalue":0,"mutation":""},{"gene":"NDUFV2","log2":-0.7106717893,"sampleID":"TCGA-B0-5703","pvalue":0,"mutation":""},{"gene":"NDUFV3","log2":-0.684007813,"sampleID":"TCGA-B0-5703","pvalue":0,"mutation":""},{"gene":"NFE2L2","log2":-0.4199868176,"sampleID":"TCGA-B0-5703","pvalue":0,"mutation":""},{"gene":"NFS1","log2":-0.6223103148,"sampleID":"TCGA-B0-5703","pvalue":0,"mutation":""},{"gene":"NFU1","log2":-0.9873615987,"sampleID":"TCGA-B0-5703","pvalue":0,"mutation":""},{"gene":"NME3","log2":0.0828102964,"sampleID":"TCGA-B0-5703","pvalue":0,"mutation":""},{"gene":"NME4","log2":0.7592810868,"sampleID":"TCGA-B0-5703","pvalue":0,"mutation":""},{"gene":"NME6","log2":-1.275186968,"sampleID":"TCGA-B0-5703","pvalue":0,"mutation":""},{"gene":"NRF1","log2":0.3446395286,"sampleID":"TCGA-B0-5703","pvalue":0,"mutation":""},{"gene":"NSUN2","log2":0.6462658531,"sampleID":"TCGA-B0-5703","pvalue":0,"mutation":""},{"gene":"NTHL1","log2":-0.3522237131,"sampleID":"TCGA-B0-5703","pvalue":0,"mutation":""},{"gene":"NUBP1","log2":0.1526899336,"sampleID":"TCGA-B0-5703","pvalue":0,"mutation":""},{"gene":"NUBP2","log2":0.1580235407,"sampleID":"TCGA-B0-5703","pvalue":0,"mutation":""},{"gene":"NUBPL","log2":-1.0401376938,"sampleID":"TCGA-B0-5703","pvalue":0,"mutation":""},{"gene":"OGDH","log2":0.2595659884,"sampleID":"TCGA-B0-5703","pvalue":0,"mutation":""},{"gene":"OGG1","log2":-0.8480002774,"sampleID":"TCGA-B0-5703","pvalue":0,"mutation":""},{"gene":"OMA1","log2":-2.2234250694,"sampleID":"TCGA-B0-5703","pvalue":0,"mutation":""},{"gene":"OPA1","log2":-0.2049755615,"sampleID":"TCGA-B0-5703","pvalue":0,"mutation":""},{"gene":"OPA3","log2":0.4354854395,"sampleID":"TCGA-B0-5703","pvalue":0,"mutation":""},{"gene":"OSGEPL1","log2":0.2286141289,"sampleID":"TCGA-B0-5703","pvalue":0,"mutation":""},{"gene":"OXA1L","log2":0.5230764594,"sampleID":"TCGA-B0-5703","pvalue":0,"mutation":""},{"gene":"PACS2","log2":0.7675360581,"sampleID":"TCGA-B0-5703","pvalue":0,"mutation":""},{"gene":"PARK2","log2":-0.6480306097,"sampleID":"TCGA-B0-5703","pvalue":0,"mutation":""},{"gene":"PARL","log2":-0.5018734951,"sampleID":"TCGA-B0-5703","pvalue":0,"mutation":""},{"gene":"PARS2","log2":-1.0034671322,"sampleID":"TCGA-B0-5703","pvalue":0,"mutation":""},{"gene":"PDHA1","log2":-1.6464166086,"sampleID":"TCGA-B0-5703","pvalue":0,"mutation":""},{"gene":"PDHB","log2":-1.8379802256,"sampleID":"TCGA-B0-5703","pvalue":0,"mutation":""},{"gene":"PDHX","log2":-0.8820256698,"sampleID":"TCGA-B0-5703","pvalue":0,"mutation":""},{"gene":"PFKL","log2":0.6840907988,"sampleID":"TCGA-B0-5703","pvalue":0,"mutation":""},{"gene":"PFKM","log2":-1.5521593729,"sampleID":"TCGA-B0-5703","pvalue":0,"mutation":""},{"gene":"PFKP","log2":1.5143135051,"sampleID":"TCGA-B0-5703","pvalue":0,"mutation":""},{"gene":"PGAM1","log2":-0.2456149077,"sampleID":"TCGA-B0-5703","pvalue":0,"mutation":""},{"gene":"PGAM2","log2":-3.6265923869,"sampleID":"TCGA-B0-5703","pvalue":0,"mutation":""},{"gene":"PGK1","log2":0.4022121993,"sampleID":"TCGA-B0-5703","pvalue":0,"mutation":""},{"gene":"PGS1","log2":-0.2381066361,"sampleID":"TCGA-B0-5703","pvalue":0,"mutation":""},{"gene":"PHB2","log2":0.1694931454,"sampleID":"TCGA-B0-5703","pvalue":0,"mutation":""},{"gene":"PHB","log2":-0.5654247664,"sampleID":"TCGA-B0-5703","pvalue":0,"mutation":""},{"gene":"PINK1","log2":-1.4553688952,"sampleID":"TCGA-B0-5703","pvalue":0,"mutation":""},{"gene":"PKIA","log2":-3.0596695152,"sampleID":"TCGA-B0-5703","pvalue":0,"mutation":""},{"gene":"PKLR","log2":2.8361086581,"sampleID":"TCGA-B0-5703","pvalue":0,"mutation":""},{"gene":"PKM2","log2":0.5187231803,"sampleID":"TCGA-B0-5703","pvalue":0,"mutation":""},{"gene":"PLD6","log2":0.7363874932,"sampleID":"TCGA-B0-5703","pvalue":0,"mutation":""},{"gene":"PMAIP1","log2":-1.9282641902,"sampleID":"TCGA-B0-5703","pvalue":0,"mutation":""},{"gene":"PML","log2":1.2684427657,"sampleID":"TCGA-B0-5703","pvalue":0,"mutation":""},{"gene":"PMPCA","log2":-0.3125343426,"sampleID":"TCGA-B0-5703","pvalue":0,"mutation":""},{"gene":"PMPCB","log2":-0.9808490279,"sampleID":"TCGA-B0-5703","pvalue":0,"mutation":""},{"gene":"POLG2","log2":-0.1445310375,"sampleID":"TCGA-B0-5703","pvalue":0,"mutation":""},{"gene":"POLG","log2":0.8701672505,"sampleID":"TCGA-B0-5703","pvalue":0,"mutation":""},{"gene":"POLRMT","log2":0.3772043574,"sampleID":"TCGA-B0-5703","pvalue":0,"mutation":""},{"gene":"PPARGC1A","log2":-1.4848344014,"sampleID":"TCGA-B0-5703","pvalue":0,"mutation":""},{"gene":"PPIA","log2":0.3617910104,"sampleID":"TCGA-B0-5703","pvalue":0,"mutation":""},{"gene":"PPIF","log2":-1.8392453686,"sampleID":"TCGA-B0-5703","pvalue":0,"mutation":""},{"gene":"PPOX","log2":-0.6771725805,"sampleID":"TCGA-B0-5703","pvalue":0,"mutation":""},{"gene":"PRDX3","log2":-1.8756387866,"sampleID":"TCGA-B0-5703","pvalue":0,"mutation":""},{"gene":"PTCD2","log2":-1.0270520057,"sampleID":"TCGA-B0-5703","pvalue":0,"mutation":""},{"gene":"PTCD3","log2":-0.4448895524,"sampleID":"TCGA-B0-5703","pvalue":0,"mutation":""},{"gene":"PTPMT1","log2":-0.8553575895,"sampleID":"TCGA-B0-5703","pvalue":0,"mutation":""},{"gene":"PUS1","log2":1.3190017497,"sampleID":"TCGA-B0-5703","pvalue":0,"mutation":""},{"gene":"PUS3","log2":0.2855560648,"sampleID":"TCGA-B0-5703","pvalue":0,"mutation":""},{"gene":"QRSL1","log2":-0.3177962677,"sampleID":"TCGA-B0-5703","pvalue":0,"mutation":""},{"gene":"QTRT1","log2":0.599935249,"sampleID":"TCGA-B0-5703","pvalue":0,"mutation":""},{"gene":"QTRTD1","log2":-0.57236978,"sampleID":"TCGA-B0-5703","pvalue":0,"mutation":""},{"gene":"RARS2","log2":-0.33154429,"sampleID":"TCGA-B0-5703","pvalue":0,"mutation":""},{"gene":"RHOT1","log2":-0.5321532191,"sampleID":"TCGA-B0-5703","pvalue":0,"mutation":""},{"gene":"RHOT2","log2":0.1724001899,"sampleID":"TCGA-B0-5703","pvalue":0,"mutation":""},{"gene":"RMRP","log2":0.1755296915,"sampleID":"TCGA-B0-5703","pvalue":0,"mutation":""},{"gene":"RNASEH1","log2":0.0943009603,"sampleID":"TCGA-B0-5703","pvalue":0,"mutation":""},{"gene":"RNASEL","log2":-0.4421880557,"sampleID":"TCGA-B0-5703","pvalue":0,"mutation":""},{"gene":"RPUSD2","log2":-0.005639373,"sampleID":"TCGA-B0-5703","pvalue":0,"mutation":""},{"gene":"RPUSD4","log2":0.1742181742,"sampleID":"TCGA-B0-5703","pvalue":0,"mutation":""},{"gene":"RRM2B","log2":-0.53535858,"sampleID":"TCGA-B0-5703","pvalue":0,"mutation":""},{"gene":"SAMM50","log2":-0.1584182267,"sampleID":"TCGA-B0-5703","pvalue":0,"mutation":""},{"gene":"SARS2","log2":-0.5984949381,"sampleID":"TCGA-B0-5703","pvalue":0,"mutation":""},{"gene":"SCO1","log2":-0.6138462544,"sampleID":"TCGA-B0-5703","pvalue":0,"mutation":""},{"gene":"SCO2","log2":0.7752516351,"sampleID":"TCGA-B0-5703","pvalue":0,"mutation":""},{"gene":"SDHAF1","log2":-0.4039189894,"sampleID":"TCGA-B0-5703","pvalue":0,"mutation":""},{"gene":"SDHAF2","log2":-0.0965879715,"sampleID":"TCGA-B0-5703","pvalue":0,"mutation":""},{"gene":"SDHA","log2":-0.2947489255,"sampleID":"TCGA-B0-5703","pvalue":0,"mutation":""},{"gene":"SDHB","log2":-2.0171438272,"sampleID":"TCGA-B0-5703","pvalue":0,"mutation":""},{"gene":"SDHC","log2":-0.5420840909,"sampleID":"TCGA-B0-5703","pvalue":0,"mutation":""},{"gene":"SDHD","log2":-1.3158564623,"sampleID":"TCGA-B0-5703","pvalue":0,"mutation":""},{"gene":"SH3GLB1","log2":-0.6506808779,"sampleID":"TCGA-B0-5703","pvalue":0,"mutation":""},{"gene":"SHC1","log2":0.915698784,"sampleID":"TCGA-B0-5703","pvalue":0,"mutation":""},{"gene":"SIGMAR1","log2":0.2786104325,"sampleID":"TCGA-B0-5703","pvalue":0,"mutation":""},{"gene":"SLC24A6","log2":-0.6194935485,"sampleID":"TCGA-B0-5703","pvalue":0,"mutation":""},{"gene":"SLC25A19","log2":0.3712747748,"sampleID":"TCGA-B0-5703","pvalue":0,"mutation":""},{"gene":"SLC25A1","log2":0.3214254608,"sampleID":"TCGA-B0-5703","pvalue":0,"mutation":""},{"gene":"SLC25A20","log2":-0.9263373143,"sampleID":"TCGA-B0-5703","pvalue":0,"mutation":""},{"gene":"SLC25A28","log2":-0.3653970233,"sampleID":"TCGA-B0-5703","pvalue":0,"mutation":""},{"gene":"SLC25A33","log2":-2.2984604153,"sampleID":"TCGA-B0-5703","pvalue":0,"mutation":""},{"gene":"SLC25A37","log2":-0.0630944653,"sampleID":"TCGA-B0-5703","pvalue":0,"mutation":""},{"gene":"SLC25A3","log2":-0.985717991,"sampleID":"TCGA-B0-5703","pvalue":0,"mutation":""},{"gene":"SLC25A4","log2":-1.9836585275,"sampleID":"TCGA-B0-5703","pvalue":0,"mutation":""},{"gene":"SLC25A5","log2":-1.6416298467,"sampleID":"TCGA-B0-5703","pvalue":0,"mutation":""},{"gene":"SLC25A6","log2":-1.1801369489,"sampleID":"TCGA-B0-5703","pvalue":0,"mutation":""},{"gene":"SLC27A1","log2":0.1782739894,"sampleID":"TCGA-B0-5703","pvalue":0,"mutation":""},{"gene":"SLC27A2","log2":1.944943558,"sampleID":"TCGA-B0-5703","pvalue":0,"mutation":""},{"gene":"SLC27A3","log2":0.536793352,"sampleID":"TCGA-B0-5703","pvalue":0,"mutation":""},{"gene":"SLC27A4","log2":-0.7632830639,"sampleID":"TCGA-B0-5703","pvalue":0,"mutation":""},{"gene":"SLC27A5","log2":-1.5785678338,"sampleID":"TCGA-B0-5703","pvalue":0,"mutation":""},{"gene":"SLC29A1","log2":-0.7222324157,"sampleID":"TCGA-B0-5703","pvalue":0,"mutation":""},{"gene":"SLC2A1","log2":1.0110651212,"sampleID":"TCGA-B0-5703","pvalue":0,"mutation":""},{"gene":"SLC2A2","log2":4.5909799114,"sampleID":"TCGA-B0-5703","pvalue":0,"mutation":""},{"gene":"SLC2A3","log2":1.7591804921,"sampleID":"TCGA-B0-5703","pvalue":0,"mutation":""},{"gene":"SLC2A4","log2":0.7078949167,"sampleID":"TCGA-B0-5703","pvalue":0,"mutation":""},{"gene":"SLC2A5","log2":4.814223083,"sampleID":"TCGA-B0-5703","pvalue":0,"mutation":""},{"gene":"SOD1","log2":-0.7481894713,"sampleID":"TCGA-B0-5703","pvalue":0,"mutation":""},{"gene":"SOD2","log2":0.7745931904,"sampleID":"TCGA-B0-5703","pvalue":0,"mutation":""},{"gene":"SPG7","log2":-0.1767218356,"sampleID":"TCGA-B0-5703","pvalue":0,"mutation":""},{"gene":"SQSTM1","log2":0.0575179315,"sampleID":"TCGA-B0-5703","pvalue":0,"mutation":""},{"gene":"SSBP1","log2":0.2938234548,"sampleID":"TCGA-B0-5703","pvalue":0,"mutation":""},{"gene":"STOML2","log2":-0.1959908055,"sampleID":"TCGA-B0-5703","pvalue":0,"mutation":""},{"gene":"SUCLA2","log2":-1.0198335291,"sampleID":"TCGA-B0-5703","pvalue":0,"mutation":""},{"gene":"SUCLG1","log2":-2.0236376907,"sampleID":"TCGA-B0-5703","pvalue":0,"mutation":""},{"gene":"SUCLG2","log2":-1.6657224931,"sampleID":"TCGA-B0-5703","pvalue":0,"mutation":""},{"gene":"SURF1","log2":-0.6208900266,"sampleID":"TCGA-B0-5703","pvalue":0,"mutation":""},{"gene":"SYBU","log2":2.6888021094,"sampleID":"TCGA-B0-5703","pvalue":0,"mutation":""},{"gene":"TACO1","log2":-0.1627350549,"sampleID":"TCGA-B0-5703","pvalue":0,"mutation":""},{"gene":"TARS2","log2":0.1460553575,"sampleID":"TCGA-B0-5703","pvalue":0,"mutation":""},{"gene":"TAZ","log2":0.4247416462,"sampleID":"TCGA-B0-5703","pvalue":0,"mutation":""},{"gene":"TCHP","log2":0.4374779994,"sampleID":"TCGA-B0-5703","pvalue":0,"mutation":""},{"gene":"TFAM","log2":-1.403416503,"sampleID":"TCGA-B0-5703","pvalue":0,"mutation":""},{"gene":"TFB1M","log2":-0.5771827056,"sampleID":"TCGA-B0-5703","pvalue":0,"mutation":""},{"gene":"TFB2M","log2":-1.3783105948,"sampleID":"TCGA-B0-5703","pvalue":0,"mutation":""},{"gene":"TIMM10","log2":-0.1727058058,"sampleID":"TCGA-B0-5703","pvalue":0,"mutation":""},{"gene":"TIMM13","log2":0.2260006015,"sampleID":"TCGA-B0-5703","pvalue":0,"mutation":""},{"gene":"TIMM17A","log2":-0.8751668862,"sampleID":"TCGA-B0-5703","pvalue":0,"mutation":""},{"gene":"TIMM17B","log2":-0.8796242816,"sampleID":"TCGA-B0-5703","pvalue":0,"mutation":""},{"gene":"TIMM22","log2":-0.0952899287,"sampleID":"TCGA-B0-5703","pvalue":0,"mutation":""},{"gene":"TIMM44","log2":0.2300355361,"sampleID":"TCGA-B0-5703","pvalue":0,"mutation":""},{"gene":"TIMM50","log2":-0.013296333,"sampleID":"TCGA-B0-5703","pvalue":0,"mutation":""},{"gene":"TIMM8A","log2":-0.2366138343,"sampleID":"TCGA-B0-5703","pvalue":0,"mutation":""},{"gene":"TIMM8B","log2":-0.9654487309,"sampleID":"TCGA-B0-5703","pvalue":0,"mutation":""},{"gene":"TIMM9","log2":0.2322250786,"sampleID":"TCGA-B0-5703","pvalue":0,"mutation":""},{"gene":"TK2","log2":-0.1702072143,"sampleID":"TCGA-B0-5703","pvalue":0,"mutation":""},{"gene":"TMEM126B","log2":-0.4680928559,"sampleID":"TCGA-B0-5703","pvalue":0,"mutation":""},{"gene":"TMEM70","log2":-0.3630260376,"sampleID":"TCGA-B0-5703","pvalue":0,"mutation":""},{"gene":"TOMM20","log2":-0.9078343816,"sampleID":"TCGA-B0-5703","pvalue":0,"mutation":""},{"gene":"TOMM22","log2":-0.5474844136,"sampleID":"TCGA-B0-5703","pvalue":0,"mutation":""},{"gene":"TOMM40L","log2":-0.6557720669,"sampleID":"TCGA-B0-5703","pvalue":0,"mutation":""},{"gene":"TOMM40","log2":0.7565354672,"sampleID":"TCGA-B0-5703","pvalue":0,"mutation":""},{"gene":"TOMM5","log2":-0.2368407209,"sampleID":"TCGA-B0-5703","pvalue":0,"mutation":""},{"gene":"TOMM6","log2":-0.8084339846,"sampleID":"TCGA-B0-5703","pvalue":0,"mutation":""},{"gene":"TOMM70A","log2":-0.5858243069,"sampleID":"TCGA-B0-5703","pvalue":0,"mutation":""},{"gene":"TOMM7","log2":0.2857038686,"sampleID":"TCGA-B0-5703","pvalue":0,"mutation":""},{"gene":"TOP1MT","log2":1.3979379021,"sampleID":"TCGA-B0-5703","pvalue":0,"mutation":""},{"gene":"TOP3A","log2":0.8958650568,"sampleID":"TCGA-B0-5703","pvalue":0,"mutation":""},{"gene":"TP53","log2":0.9636782969,"sampleID":"TCGA-B0-5703","pvalue":0,"mutation":""},{"gene":"TPI1","log2":0.5698271596,"sampleID":"TCGA-B0-5703","pvalue":0,"mutation":""},{"gene":"TRAK1","log2":-0.6231057325,"sampleID":"TCGA-B0-5703","pvalue":0,"mutation":""},{"gene":"TRAK2","log2":-0.9370765327,"sampleID":"TCGA-B0-5703","pvalue":0,"mutation":""},{"gene":"TRAP1","log2":0.697018201,"sampleID":"TCGA-B0-5703","pvalue":0,"mutation":""},{"gene":"TRIT1","log2":-1.1047719326,"sampleID":"TCGA-B0-5703","pvalue":0,"mutation":""},{"gene":"TRMT112","log2":0.060934984,"sampleID":"TCGA-B0-5703","pvalue":0,"mutation":""},{"gene":"TRMT11","log2":-0.1799034313,"sampleID":"TCGA-B0-5703","pvalue":0,"mutation":""},{"gene":"TRMT1","log2":0.9637284924,"sampleID":"TCGA-B0-5703","pvalue":0,"mutation":""},{"gene":"TRMT2B","log2":-0.6060912573,"sampleID":"TCGA-B0-5703","pvalue":0,"mutation":""},{"gene":"TRMT5","log2":-0.1559416617,"sampleID":"TCGA-B0-5703","pvalue":0,"mutation":""},{"gene":"TRMT61B","log2":-0.1216259077,"sampleID":"TCGA-B0-5703","pvalue":0,"mutation":""},{"gene":"TRMT6","log2":-1.2860363922,"sampleID":"TCGA-B0-5703","pvalue":0,"mutation":""},{"gene":"TRMU","log2":-0.7621892551,"sampleID":"TCGA-B0-5703","pvalue":0,"mutation":""},{"gene":"TRNT1","log2":-2.1426998798,"sampleID":"TCGA-B0-5703","pvalue":0,"mutation":""},{"gene":"TRUB2","log2":-0.4294946108,"sampleID":"TCGA-B0-5703","pvalue":0,"mutation":""},{"gene":"TSFM","log2":-0.7097003356,"sampleID":"TCGA-B0-5703","pvalue":0,"mutation":""},{"gene":"TTC19","log2":-1.1082764634,"sampleID":"TCGA-B0-5703","pvalue":0,"mutation":""},{"gene":"TUFM","log2":-0.6903715478,"sampleID":"TCGA-B0-5703","pvalue":0,"mutation":""},{"gene":"TXN2","log2":-0.6931324981,"sampleID":"TCGA-B0-5703","pvalue":0,"mutation":""},{"gene":"TXNRD2","log2":-0.3714720535,"sampleID":"TCGA-B0-5703","pvalue":0,"mutation":""},{"gene":"UNG","log2":-0.6520522883,"sampleID":"TCGA-B0-5703","pvalue":0,"mutation":""},{"gene":"UQCC","log2":-0.4601480394,"sampleID":"TCGA-B0-5703","pvalue":0,"mutation":""},{"gene":"UQCR10","log2":-1.2044806618,"sampleID":"TCGA-B0-5703","pvalue":0,"mutation":""},{"gene":"UQCR11","log2":-1.1017423268,"sampleID":"TCGA-B0-5703","pvalue":0,"mutation":""},{"gene":"UQCRB","log2":-1.016727463,"sampleID":"TCGA-B0-5703","pvalue":0,"mutation":""},{"gene":"UQCRC1","log2":-1.6512547223,"sampleID":"TCGA-B0-5703","pvalue":0,"mutation":""},{"gene":"UQCRC2","log2":-1.183888522,"sampleID":"TCGA-B0-5703","pvalue":0,"mutation":""},{"gene":"UQCRFS1","log2":-1.6472813398,"sampleID":"TCGA-B0-5703","pvalue":0,"mutation":""},{"gene":"UQCRH","log2":-3.9198128995,"sampleID":"TCGA-B0-5703","pvalue":0,"mutation":""},{"gene":"UQCRQ","log2":-1.233014375,"sampleID":"TCGA-B0-5703","pvalue":0,"mutation":""},{"gene":"UROD","log2":-0.7903092614,"sampleID":"TCGA-B0-5703","pvalue":0,"mutation":""},{"gene":"UROS","log2":-1.4025206133,"sampleID":"TCGA-B0-5703","pvalue":0,"mutation":""},{"gene":"VARS2","log2":0.5189671718,"sampleID":"TCGA-B0-5703","pvalue":0,"mutation":""},{"gene":"VDAC1","log2":-0.4439707904,"sampleID":"TCGA-B0-5703","pvalue":0,"mutation":""},{"gene":"VDAC2","log2":-1.4244074246,"sampleID":"TCGA-B0-5703","pvalue":0,"mutation":""},{"gene":"VDAC3","log2":-0.68692996,"sampleID":"TCGA-B0-5703","pvalue":0,"mutation":""},{"gene":"WARS2","log2":0.2528809506,"sampleID":"TCGA-B0-5703","pvalue":0,"mutation":""},{"gene":"XIAP","log2":-0.1091618832,"sampleID":"TCGA-B0-5703","pvalue":0,"mutation":""},{"gene":"YARS2","log2":-0.1895024228,"sampleID":"TCGA-B0-5703","pvalue":0,"mutation":""},{"gene":"YME1L1","log2":-0.1800784512,"sampleID":"TCGA-B0-5703","pvalue":0,"mutation":""},{"gene":"YRDC","log2":-0.9532550804,"sampleID":"TCGA-B0-5703","pvalue":0,"mutation":""}]