[{"sampleID":"TCGA-38-4626","PC1":-6.7239,"PC2":3.6513,"PC3":1.1269,"group":"LUAD","gender":"FEMALE","stage":"[NA]","vital":"Alive","neg3":"[NA]","url":"./data/TCGA/LUAD/TCGA-38-4626.json"},{"sampleID":"TCGA-38-4632","PC1":-3.1229,"PC2":-1.384,"PC3":-2.4193,"group":"LUAD","gender":"MALE","stage":"Stage IV","vital":"Dead","neg3":"[NA]","url":"./data/TCGA/LUAD/TCGA-38-4632.json"},{"sampleID":"TCGA-44-2655","PC1":5.6233,"PC2":2.0627,"PC3":-1.671,"group":"LUAD","gender":"FEMALE","stage":"Stage I","vital":"Alive","neg3":"[NA]","url":"./data/TCGA/LUAD/TCGA-44-2655.json"},{"sampleID":"TCGA-49-4490","PC1":-1.309,"PC2":-4.763,"PC3":1.0198,"group":"LUAD","gender":"FEMALE","stage":"Stage III","vital":"Dead","neg3":"[NA]","url":"./data/TCGA/LUAD/TCGA-49-4490.json"},{"sampleID":"TCGA-49-6742","PC1":5.5325,"PC2":0.4329,"PC3":1.9437,"group":"LUAD","gender":"MALE","stage":"Stage II","vital":"Alive","neg3":"[NA]","url":"./data/TCGA/LUAD/TCGA-49-6742.json"}]
